{"team": {"number": "71251F", "program": "VRC", "team_name": "F", "robot_name": "", "organisation": "ERNEST BECKER MIDDLE SCHOOL", "city": "Las Vegas", "region": "Nevada", "country": "United States", "grade": "High School", "is_registered": 0}, "events": [{"sku": "RE-VRC-19-0346", "key": "RE-VRC-19-0346", "program": "VRC", "name": "Nevada State VRC Middle School Championship (STEAM Career Expo)", "loc_venue": "Sunrise Mountain High School", "loc_address1": "2575 Los Feliz Street", "loc_address2": "", "loc_city": "Las Vegas", "loc_region": "Nevada", "loc_postcode": "89156", "loc_country": "United States", "season": "Tower Takeover", "start": "2020-02-28T00:00:00+00:00", "end": "2020-02-29T23:59:59+00:00", "divisions": ["Division 1"]}, {"sku": "RE-VRC-19-0541", "key": "RE-VRC-19-0541", "program": "VRC", "name": "VRC Coronado High School Qualifier", "loc_venue": "Coronado High School", "loc_address1": "1001 Coronado Center Drive", "loc_address2": "", "loc_city": "Henderson", "loc_region": "Nevada", "loc_postcode": "89052", "loc_country": "United States", "season": "Tower Takeover", "start": "2020-02-15T00:00:00+00:00", "end": "2020-02-15T23:59:59+00:00", "divisions": ["Division 1"]}, {"sku": "RE-VRC-19-9405", "key": "RE-VRC-19-9405", "program": "VRC", "name": "VRC Performance Only Competition @ Lied STEM Academy", "loc_venue": "Lied STEM Academy", "loc_address1": "5350 West Tropical Parkway", "loc_address2": "", "loc_city": "Las Vegas", "loc_region": "Nevada", "loc_postcode": "89130", "loc_country": "United States", "season": "Tower Takeover", "start": "2019-11-09T00:00:00+00:00", "end": "2019-11-09T23:59:59+00:00", "divisions": ["Division 1"]}], "matches": [{"sku": "RE-VRC-19-0346", "division": "Division 1", "round": 2, "instance": 1, "matchnum": 8, "field": "Technology", "red1": "11462C", "red2": "71251F", "red3": "", "redsit": "", "blue1": "71251G", "blue2": "89100A", "blue3": "", "bluesit": "", "redscore": 28, "bluescore": 12, "scored": 1, "scheduled": "2020-02-29T18:24:30+00:00"}, {"sku": "RE-VRC-19-0346", "division": "Division 1", "round": 2, "instance": 1, "matchnum": 17, "field": "Technology", "red1": "21800A", "red2": "71251E", "red3": "", "redsit": "", "blue1": "10010B", "blue2": "71251F", "blue3": "", "bluesit": "", "redscore": 6, "bluescore": 8, "scored": 1, "scheduled": "2020-02-29T18:56:00+00:00"}, {"sku": "RE-VRC-19-0346", "division": "Division 1", "round": 2, "instance": 1, "matchnum": 26, "field": "Technology", "red1": "92699S", "red2": "92882H", "red3": "", "redsit": "", "blue1": "99558A", "blue2": "71251F", "blue3": "", "bluesit": "", "redscore": 3, "bluescore": 10, "scored": 1, "scheduled": "2020-02-29T19:27:30+00:00"}, {"sku": "RE-VRC-19-0346", "division": "Division 1", "round": 2, "instance": 1, "matchnum": 39, "field": "Engineering", "red1": "71251F", "red2": "10058B", "red3": "", "redsit": "", "blue1": "89100B", "blue2": "71251C", "blue3": "", "bluesit": "", "redscore": 7, "bluescore": 8, "scored": 1, "scheduled": "2020-02-29T21:06:00+00:00"}, {"sku": "RE-VRC-19-0346", "division": "Division 1", "round": 2, "instance": 1, "matchnum": 55, "field": "Science", "red1": "75693B", "red2": "92882Z", "red3": "", "redsit": "", "blue1": "71251B", "blue2": "71251F", "blue3": "", "bluesit": "", "redscore": 10, "bluescore": 3, "scored": 1, "scheduled": "2020-02-29T21:54:00+00:00"}, {"sku": "RE-VRC-19-0346", "division": "Division 1", "round": 2, "instance": 1, "matchnum": 64, "field": "Science", "red1": "11462D", "red2": "71251F", "red3": "", "redsit": "", "blue1": "89002A", "blue2": "530B", "blue3": "", "bluesit": "", "redscore": 31, "bluescore": 9, "scored": 1, "scheduled": "2020-02-29T22:21:00+00:00"}, {"sku": "RE-VRC-19-0346", "division": "Division 1", "round": 6, "instance": 2, "matchnum": 1, "field": "", "red1": "10058B", "red2": "71251C", "red3": "", "redsit": "", "blue1": "71251F", "blue2": "92882X", "blue3": "", "bluesit": "", "redscore": 26, "bluescore": 6, "scored": 1, "scheduled": "1970-01-01T00:00:00+00:00"}, {"sku": "RE-VRC-19-0541", "division": "Division 1", "round": 2, "instance": 1, "matchnum": 11, "field": "Field 2", "red1": "74177H", "red2": "64B", "red3": "", "redsit": "", "blue1": "71251F", "blue2": "11462D", "blue3": "", "bluesit": "", "redscore": 10, "bluescore": 25, "scored": 1, "scheduled": "2020-02-15T17:55:00+00:00"}, {"sku": "RE-VRC-19-0541", "division": "Division 1", "round": 2, "instance": 1, "matchnum": 20, "field": "Field 2", "red1": "71251F", "red2": "945V", "red3": "", "redsit": "", "blue1": "64A", "blue2": "30417D", "blue3": "", "bluesit": "", "redscore": 12, "bluescore": 20, "scored": 1, "scheduled": "2020-02-15T18:22:00+00:00"}, {"sku": "RE-VRC-19-0541", "division": "Division 1", "round": 2, "instance": 1, "matchnum": 33, "field": "Field 3", "red1": "71251F", "red2": "6891Z", "red3": "", "redsit": "", "blue1": "71251A", "blue2": "11462B", "blue3": "", "bluesit": "", "redscore": 15, "bluescore": 3, "scored": 1, "scheduled": "2020-02-15T19:01:00+00:00"}, {"sku": "RE-VRC-19-0541", "division": "Division 1", "round": 2, "instance": 1, "matchnum": 61, "field": "Field 1", "red1": "945Y", "red2": "64W", "red3": "", "redsit": "", "blue1": "71251F", "blue2": "92882H", "blue3": "", "bluesit": "", "redscore": 22, "bluescore": 10, "scored": 1, "scheduled": "2020-02-15T21:09:00+00:00"}, {"sku": "RE-VRC-19-0541", "division": "Division 1", "round": 2, "instance": 1, "matchnum": 71, "field": "Field 2", "red1": "7853A", "red2": "7870X", "red3": "", "redsit": "", "blue1": "8871B", "blue2": "71251F", "blue3": "", "bluesit": "", "redscore": 24, "bluescore": 9, "scored": 1, "scheduled": "2020-02-15T21:39:00+00:00"}, {"sku": "RE-VRC-19-0541", "division": "Division 1", "round": 2, "instance": 1, "matchnum": 86, "field": "Field 2", "red1": "92882X", "red2": "7853B", "red3": "", "redsit": "", "blue1": "71251F", "blue2": "7870H", "blue3": "", "bluesit": "", "redscore": 13, "bluescore": 8, "scored": 1, "scheduled": "2020-02-15T22:24:00+00:00"}, {"sku": "RE-VRC-19-9405", "division": "Division 1", "round": 2, "instance": 1, "matchnum": 1, "field": "Field 1", "red1": "945Z", "red2": "71251F", "red3": "", "redsit": "", "blue1": "11462H", "blue2": "71300E", "blue3": "", "bluesit": "", "redscore": 12, "bluescore": 9, "scored": 1, "scheduled": "2019-11-09T18:45:00+00:00"}, {"sku": "RE-VRC-19-9405", "division": "Division 1", "round": 2, "instance": 1, "matchnum": 11, "field": "Field 1", "red1": "30417C", "red2": "7853C", "red3": "", "redsit": "", "blue1": "7853A", "blue2": "71251F", "blue3": "", "bluesit": "", "redscore": 2, "bluescore": 10, "scored": 1, "scheduled": "2019-11-09T19:25:00+00:00"}, {"sku": "RE-VRC-19-9405", "division": "Division 1", "round": 2, "instance": 1, "matchnum": 21, "field": "Field 1", "red1": "71251F", "red2": "71251C", "red3": "", "redsit": "", "blue1": "71251E", "blue2": "71300D", "blue3": "", "bluesit": "", "redscore": 3, "bluescore": 10, "scored": 1, "scheduled": "2019-11-09T21:04:00+00:00"}, {"sku": "RE-VRC-19-9405", "division": "Division 1", "round": 2, "instance": 1, "matchnum": 29, "field": "Field 1", "red1": "945T", "red2": "987A", "red3": "", "redsit": "", "blue1": "71251F", "blue2": "945G", "blue3": "", "bluesit": "", "redscore": 38, "bluescore": 10, "scored": 1, "scheduled": "2019-11-09T21:36:00+00:00"}, {"sku": "RE-VRC-19-9405", "division": "Division 1", "round": 2, "instance": 1, "matchnum": 40, "field": "Field 2", "red1": "71251B", "red2": "71251F", "red3": "", "redsit": "", "blue1": "987C", "blue2": "8871A", "blue3": "", "bluesit": "", "redscore": 10, "bluescore": 22, "scored": 1, "scheduled": "2019-11-09T22:20:00+00:00"}], "rankings": [{"sku": "RE-VRC-19-0346", "division": "Division 1", "rank": 12, "team": "71251F", "wins": 4, "losses": 2, "ties": 0, "wp": 8, "ap": 24, "sp": 40, "trsp": 2, "max_score": 31, "opr": 5.79269, "dpr": 1.87703, "ccwm": 3.91566}, {"sku": "RE-VRC-19-0541", "division": "Division 1", "rank": 37, "team": "71251F", "wins": 2, "losses": 4, "ties": 0, "wp": 4, "ap": 21, "sp": 52, "trsp": 35, "max_score": 25, "opr": 4.56464, "dpr": 4.22341, "ccwm": 0.341228}, {"sku": "RE-VRC-19-9405", "division": "Division 1", "rank": 27, "team": "71251F", "wins": 2, "losses": 3, "ties": 0, "wp": 4, "ap": 3, "sp": 34, "trsp": 14, "max_score": 12, "opr": 4.54418, "dpr": 10.682, "ccwm": -6.13779}], "season_rankings": [{"team": "71251F", "season": "Tower Takeover", "program": "VRC", "vrating_rank": 5768, "vrating": 11.382580051887}], "awards": [], "skills": []}