{"team": {"number": "71610A", "program": "VRC", "team_name": "Sponsored By", "robot_name": "", "organisation": "GORDON PARKS ACADEMY", "city": "Wichita", "region": "Kansas", "country": "United States", "grade": "High School", "is_registered": 0}, "events": [{"sku": "RE-VRC-19-9789", "key": "RE-VRC-19-9789", "program": "VRC", "name": "Kansas State Championship MS", "loc_venue": "Hesston High School", "loc_address1": "200 North Ridge Road", "loc_address2": "", "loc_city": "Hesston", "loc_region": "Kansas", "loc_postcode": "67062", "loc_country": "United States", "season": "Tower Takeover", "start": "2020-03-06T00:00:00+00:00", "end": "2020-03-06T23:59:59+00:00", "divisions": ["Division 1"]}, {"sku": "RE-VRC-19-9672", "key": "RE-VRC-19-9672", "program": "VRC", "name": "Derby Robo Challenge (MS) Only", "loc_venue": "Derby North Middle School", "loc_address1": "3100 Rock Road", "loc_address2": "", "loc_city": "Derby", "loc_region": "Kansas", "loc_postcode": "67037", "loc_country": "United States", "season": "Tower Takeover", "start": "2020-02-01T00:00:00+00:00", "end": "2020-02-01T23:59:59+00:00", "divisions": ["Division 1"]}, {"sku": "RE-VRC-19-0458", "key": "RE-VRC-19-0458", "program": "VRC", "name": "CHENEY CARDINAL CLASH ( MS Only ) Tournament", "loc_venue": "Cheney High School (MS gym)", "loc_address1": "800 North Marshall Street", "loc_address2": "", "loc_city": "Cheney", "loc_region": "Kansas", "loc_postcode": "67025", "loc_country": "United States", "season": "Tower Takeover", "start": "2020-01-25T00:00:00+00:00", "end": "2020-01-25T23:59:59+00:00", "divisions": ["Division 1"]}, {"sku": "RE-VRC-19-9533", "key": "RE-VRC-19-9533", "program": "VRC", "name": "Wranglerbot 3.0 (MS Only)", "loc_venue": "Wilbur Middle School", "loc_address1": "340 N Tyler", "loc_address2": "", "loc_city": "Wichita", "loc_region": "Kansas", "loc_postcode": "67212", "loc_country": "United States", "season": "Tower Takeover", "start": "2020-01-10T00:00:00+00:00", "end": "2020-01-10T23:59:59+00:00", "divisions": ["Division 1"]}, {"sku": "RE-VRC-19-8128", "key": "RE-VRC-19-8128", "program": "VRC", "name": "Trailblazer Bot Battle", "loc_venue": "2201 E 25th St N", "loc_address1": "2201 East 25th Street North", "loc_address2": "", "loc_city": "Wichita", "loc_region": "Kansas", "loc_postcode": "67219", "loc_country": "United States", "season": "Tower Takeover", "start": "2019-11-22T00:00:00+00:00", "end": "2019-11-22T23:59:59+00:00", "divisions": ["Division 1"]}, {"sku": "RE-VRC-19-9032", "key": "RE-VRC-19-9032", "program": "VRC", "name": "Derby Robo Spooktacular MS Only", "loc_venue": "Derby Middle School", "loc_address1": "801 East Madison Avenue", "loc_address2": "", "loc_city": "Derby", "loc_region": "Kansas", "loc_postcode": "67037", "loc_country": "United States", "season": "Tower Takeover", "start": "2019-11-02T00:00:00+00:00", "end": "2019-11-02T23:59:59+00:00", "divisions": ["Division 1"]}, {"sku": "RE-VRC-18-6399", "key": "RE-VRC-18-6399", "program": "VRC", "name": "CREATE U.S. Open Robotics Championship - VRC MIDDLE SCHOOL DIVISION", "loc_venue": "Mid-America Center", "loc_address1": "One Arena Way", "loc_address2": "", "loc_city": "Council Bluffs", "loc_region": "Iowa", "loc_postcode": "51501", "loc_country": "United States", "season": "Turning Point", "start": "2019-04-04T00:00:00+00:00", "end": "2019-04-06T23:59:59+00:00", "divisions": ["Results"]}, {"sku": "RE-VRC-19-6927", "key": "RE-VRC-19-6927", "program": "VRC", "name": "Kansas MS State Championship Tournament", "loc_venue": "ESSDACK", "loc_address1": "1500 East 11th Avenue", "loc_address2": "", "loc_city": "Hutchinson", "loc_region": "Kansas", "loc_postcode": "67501", "loc_country": "United States", "season": "Turning Point", "start": "2019-03-01T00:00:00+00:00", "end": "2019-03-01T23:59:59+00:00", "divisions": ["Division 1"]}, {"sku": "RE-VRC-18-5867", "key": "RE-VRC-18-5867", "program": "VRC", "name": "Derby Robo Challenge (MS) Only", "loc_venue": "Derby North Middle School", "loc_address1": "3100 Rock Road", "loc_address2": "", "loc_city": "Derby", "loc_region": "Kansas", "loc_postcode": "67037", "loc_country": "United States", "season": "Turning Point", "start": "2019-02-02T00:00:00+00:00", "end": "2019-02-02T23:59:59+00:00", "divisions": ["Division 1"]}, {"sku": "RE-VRC-18-6858", "key": "RE-VRC-18-6858", "program": "VRC", "name": "Wranglerbot 2.0 Turning Point (Blended)", "loc_venue": "Wilbur Middle School", "loc_address1": "340 North Tyler Road", "loc_address2": "", "loc_city": "Wichita", "loc_region": "Kansas", "loc_postcode": "67212", "loc_country": "United States", "season": "Turning Point", "start": "2019-01-09T00:00:00+00:00", "end": "2019-01-09T23:59:59+00:00", "divisions": ["Division 1"]}, {"sku": "RE-VRC-18-6533", "key": "RE-VRC-18-6533", "program": "VRC", "name": "Trailblazer Bot Battle (MS Only)", "loc_venue": "Gordon Parks Academy", "loc_address1": "2201 East 25th Street North", "loc_address2": "", "loc_city": "Wichita", "loc_region": "Kansas", "loc_postcode": "67219", "loc_country": "United States", "season": "Turning Point", "start": "2018-11-16T00:00:00+00:00", "end": "2018-11-16T23:59:59+00:00", "divisions": ["Division 1"]}, {"sku": "RE-VRC-18-5726", "key": "RE-VRC-18-5726", "program": "VRC", "name": "Derby Robo Spooktacular  ( VRC MS OnlyTurning Point ) ", "loc_venue": "Derby Middle School", "loc_address1": "801 East Madison Avenue", "loc_address2": "", "loc_city": "Derby", "loc_region": "Kansas", "loc_postcode": "67037", "loc_country": "United States", "season": "Turning Point", "start": "2018-10-30T00:00:00+00:00", "end": "2018-10-30T23:59:59+00:00", "divisions": ["Division 1"]}, {"sku": "RE-VRC-17-4565", "key": "RE-VRC-17-4565", "program": "VRC", "name": "Shocker Special-******Moved to Saturday at Hesston High School - 9:30 am******", "loc_venue": "Hesston High School", "loc_address1": "200 North Ridge Road", "loc_address2": "", "loc_city": "Hesston", "loc_region": "Kansas", "loc_postcode": "67260", "loc_country": "United States", "season": "In The Zone", "start": "2018-02-24T00:00:00+00:00", "end": "2018-02-24T23:59:59+00:00", "divisions": ["Division 1"]}, {"sku": "RE-VRC-17-4085", "key": "RE-VRC-17-4085", "program": "VRC", "name": "Derby Robo Challenge ", "loc_venue": "Derby High School", "loc_address1": "Rock Road and James Street", "loc_address2": "", "loc_city": "Derby", "loc_region": "Kansas", "loc_postcode": "67037", "loc_country": "United States", "season": "In The Zone", "start": "2018-01-27T00:00:00+00:00", "end": "2018-01-27T23:59:59+00:00", "divisions": ["Division 1"]}, {"sku": "RE-VRC-17-4319", "key": "RE-VRC-17-4319", "program": "VRC", "name": "Wrangler Bot Scrimmage", "loc_venue": "Wilbur Middle School", "loc_address1": "340 N Tyler", "loc_address2": "", "loc_city": "Wichita ", "loc_region": "Kansas", "loc_postcode": "67212", "loc_country": "United States", "season": "In The Zone", "start": "2018-01-10T00:00:00+00:00", "end": "2018-01-10T23:59:59+00:00", "divisions": ["Results"]}], "matches": [{"sku": "RE-VRC-19-9789", "division": "Division 1", "round": 2, "instance": 1, "matchnum": 2, "field": "Field 2", "red1": "25900A", "red2": "31001A", "red3": "", "redsit": "", "blue1": "66617C", "blue2": "71610A", "blue3": "", "bluesit": "", "redscore": 26, "bluescore": 20, "scored": 1, "scheduled": "2020-03-06T15:35:20+00:00"}, {"sku": "RE-VRC-19-9789", "division": "Division 1", "round": 2, "instance": 1, "matchnum": 8, "field": "Field 2", "red1": "71610A", "red2": "2036D", "red3": "", "redsit": "", "blue1": "1304X", "blue2": "67212A", "blue3": "", "bluesit": "", "redscore": 34, "bluescore": 19, "scored": 1, "scheduled": "2020-03-06T16:07:20+00:00"}, {"sku": "RE-VRC-19-9789", "division": "Division 1", "round": 2, "instance": 1, "matchnum": 16, "field": "Field 2", "red1": "26000C", "red2": "61538C", "red3": "", "redsit": "", "blue1": "2036A", "blue2": "71610A", "blue3": "", "bluesit": "", "redscore": 18, "bluescore": 17, "scored": 1, "scheduled": "2020-03-06T16:50:00+00:00"}, {"sku": "RE-VRC-19-9789", "division": "Division 1", "round": 2, "instance": 1, "matchnum": 23, "field": "Field 1", "red1": "71610A", "red2": "67206D", "red3": "", "redsit": "", "blue1": "43363B", "blue2": "71610C", "blue3": "", "bluesit": "", "redscore": 15, "bluescore": 26, "scored": 1, "scheduled": "2020-03-06T17:27:20+00:00"}, {"sku": "RE-VRC-19-9789", "division": "Division 1", "round": 2, "instance": 1, "matchnum": 30, "field": "Field 2", "red1": "61538B", "red2": "67206D", "red3": "", "redsit": "", "blue1": "71610A", "blue2": "26000F", "blue3": "", "bluesit": "", "redscore": 24, "bluescore": 14, "scored": 1, "scheduled": "2020-03-06T19:00:00+00:00"}, {"sku": "RE-VRC-19-9789", "division": "Division 1", "round": 2, "instance": 1, "matchnum": 34, "field": "Field 2", "red1": "71610A", "red2": "71610B", "red3": "", "redsit": "", "blue1": "15119A", "blue2": "61538E", "blue3": "", "bluesit": "", "redscore": 13, "bluescore": 20, "scored": 1, "scheduled": "2020-03-06T19:20:00+00:00"}, {"sku": "RE-VRC-19-9789", "division": "Division 1", "round": 6, "instance": 2, "matchnum": 1, "field": "", "red1": "2036D", "red2": "2036E", "red3": "", "redsit": "", "blue1": "71610C", "blue2": "71610A", "blue3": "", "bluesit": "", "redscore": 17, "bluescore": 21, "scored": 1, "scheduled": "1970-01-01T00:00:00+00:00"}, {"sku": "RE-VRC-19-9789", "division": "Division 1", "round": 3, "instance": 1, "matchnum": 1, "field": "", "red1": "67206E", "red2": "67206D", "red3": "", "redsit": "", "blue1": "71610C", "blue2": "71610A", "blue3": "", "bluesit": "", "redscore": 15, "bluescore": 17, "scored": 1, "scheduled": "1970-01-01T00:00:00+00:00"}, {"sku": "RE-VRC-19-9789", "division": "Division 1", "round": 4, "instance": 1, "matchnum": 1, "field": "", "red1": "71610C", "red2": "71610A", "red3": "", "redsit": "", "blue1": "26000C", "blue2": "43363B", "blue3": "", "bluesit": "", "redscore": 0, "bluescore": 26, "scored": 1, "scheduled": "1970-01-01T00:00:00+00:00"}, {"sku": "RE-VRC-19-9672", "division": "Division 1", "round": 2, "instance": 1, "matchnum": 6, "field": "FALCON FIELD", "red1": "66617A", "red2": "71610A", "red3": "", "redsit": "", "blue1": "71610X", "blue2": "31001A", "blue3": "", "bluesit": "", "redscore": 11, "bluescore": 8, "scored": 1, "scheduled": "2020-02-01T15:27:30+00:00"}, {"sku": "RE-VRC-19-9672", "division": "Division 1", "round": 2, "instance": 1, "matchnum": 13, "field": "BULLDOG FIELD", "red1": "26000D", "red2": "31001B", "red3": "", "redsit": "", "blue1": "71610A", "blue2": "71610Y", "blue3": "", "bluesit": "", "redscore": 16, "bluescore": 9, "scored": 1, "scheduled": "2020-02-01T16:00:00+00:00"}, {"sku": "RE-VRC-19-9672", "division": "Division 1", "round": 2, "instance": 1, "matchnum": 24, "field": "FALCON FIELD", "red1": "25900D", "red2": "25900A", "red3": "", "redsit": "", "blue1": "66617C", "blue2": "71610A", "blue3": "", "bluesit": "", "redscore": 11, "bluescore": 22, "scored": 1, "scheduled": "2020-02-01T16:55:00+00:00"}, {"sku": "RE-VRC-19-9672", "division": "Division 1", "round": 2, "instance": 1, "matchnum": 36, "field": "FALCON FIELD", "red1": "61538B", "red2": "71610A", "red3": "", "redsit": "", "blue1": "67210F", "blue2": "2036A", "blue3": "", "bluesit": "", "redscore": 12, "bluescore": 14, "scored": 1, "scheduled": "2020-02-01T17:55:00+00:00"}, {"sku": "RE-VRC-19-9672", "division": "Division 1", "round": 2, "instance": 1, "matchnum": 53, "field": "BULLDOG FIELD", "red1": "67206A", "red2": "67206E", "red3": "", "redsit": "", "blue1": "26000A", "blue2": "71610A", "blue3": "", "bluesit": "", "redscore": 2, "bluescore": 29, "scored": 1, "scheduled": "2020-02-01T20:02:00+00:00"}, {"sku": "RE-VRC-19-9672", "division": "Division 1", "round": 2, "instance": 1, "matchnum": 62, "field": "FALCON FIELD", "red1": "67206D", "red2": "71610A", "red3": "", "redsit": "", "blue1": "71610C", "blue2": "67206B", "blue3": "", "bluesit": "", "redscore": 19, "bluescore": 9, "scored": 1, "scheduled": "2020-02-01T20:42:30+00:00"}, {"sku": "RE-VRC-19-9672", "division": "Division 1", "round": 6, "instance": 6, "matchnum": 1, "field": "", "red1": "71610A", "red2": "71610B", "red3": "", "redsit": "", "blue1": "26000D", "blue2": "67210A", "blue3": "", "bluesit": "", "redscore": 24, "bluescore": 9, "scored": 1, "scheduled": "1970-01-01T00:00:00+00:00"}, {"sku": "RE-VRC-19-9672", "division": "Division 1", "round": 3, "instance": 3, "matchnum": 1, "field": "", "red1": "26000A", "red2": "26000C", "red3": "", "redsit": "", "blue1": "71610A", "blue2": "71610B", "blue3": "", "bluesit": "", "redscore": 15, "bluescore": 20, "scored": 1, "scheduled": "1970-01-01T00:00:00+00:00"}, {"sku": "RE-VRC-19-9672", "division": "Division 1", "round": 4, "instance": 2, "matchnum": 1, "field": "", "red1": "71610A", "red2": "71610B", "red3": "", "redsit": "", "blue1": "2036D", "blue2": "67212A", "blue3": "", "bluesit": "", "redscore": 17, "bluescore": 12, "scored": 1, "scheduled": "1970-01-01T00:00:00+00:00"}, {"sku": "RE-VRC-19-9672", "division": "Division 1", "round": 5, "instance": 1, "matchnum": 1, "field": "", "red1": "2036A", "red2": "2036B", "red3": "", "redsit": "", "blue1": "71610A", "blue2": "71610B", "blue3": "", "bluesit": "", "redscore": 39, "bluescore": 23, "scored": 1, "scheduled": "1970-01-01T00:00:00+00:00"}, {"sku": "RE-VRC-19-0458", "division": "Division 1", "round": 2, "instance": 1, "matchnum": 1, "field": "Field 1", "red1": "71610A", "red2": "71610C", "red3": "", "redsit": "", "blue1": "2036E", "blue2": "61538A", "blue3": "", "bluesit": "", "redscore": 30, "bluescore": 11, "scored": 1, "scheduled": "2020-01-25T15:30:00+00:00"}, {"sku": "RE-VRC-19-0458", "division": "Division 1", "round": 2, "instance": 1, "matchnum": 14, "field": "Field 2", "red1": "71610A", "red2": "61538D", "red3": "", "redsit": "", "blue1": "67206D", "blue2": "71610X", "blue3": "", "bluesit": "", "redscore": 64, "bluescore": 0, "scored": 1, "scheduled": "2020-01-25T16:22:00+00:00"}, {"sku": "RE-VRC-19-0458", "division": "Division 1", "round": 2, "instance": 1, "matchnum": 21, "field": "Field 1", "red1": "61538E", "red2": "71610B", "red3": "", "redsit": "", "blue1": "71610A", "blue2": "67206C", "blue3": "", "bluesit": "", "redscore": 33, "bluescore": 29, "scored": 1, "scheduled": "2020-01-25T16:50:00+00:00"}, {"sku": "RE-VRC-19-0458", "division": "Division 1", "round": 2, "instance": 1, "matchnum": 26, "field": "Field 2", "red1": "25900B", "red2": "71610Y", "red3": "", "redsit": "", "blue1": "67206B", "blue2": "71610A", "blue3": "", "bluesit": "", "redscore": 17, "bluescore": 31, "scored": 1, "scheduled": "2020-01-25T17:10:00+00:00"}, {"sku": "RE-VRC-19-0458", "division": "Division 1", "round": 2, "instance": 1, "matchnum": 40, "field": "Field 2", "red1": "71610A", "red2": "2036D", "red3": "", "redsit": "", "blue1": "61538C", "blue2": "31001C", "blue3": "", "bluesit": "", "redscore": 18, "bluescore": 8, "scored": 1, "scheduled": "2020-01-25T18:06:00+00:00"}, {"sku": "RE-VRC-19-0458", "division": "Division 1", "round": 2, "instance": 1, "matchnum": 49, "field": "Field 1", "red1": "25900C", "red2": "2036C", "red3": "", "redsit": "", "blue1": "71610A", "blue2": "2036B", "blue3": "", "bluesit": "", "redscore": 12, "bluescore": 45, "scored": 1, "scheduled": "2020-01-25T19:24:00+00:00"}, {"sku": "RE-VRC-19-0458", "division": "Division 1", "round": 6, "instance": 5, "matchnum": 1, "field": "", "red1": "71610A", "red2": "71610B", "red3": "", "redsit": "", "blue1": "67206E", "blue2": "67206D", "blue3": "", "bluesit": "", "redscore": 43, "bluescore": 15, "scored": 1, "scheduled": "1970-01-01T00:00:00+00:00"}, {"sku": "RE-VRC-19-0458", "division": "Division 1", "round": 3, "instance": 3, "matchnum": 1, "field": "", "red1": "71610A", "red2": "71610B", "red3": "", "redsit": "", "blue1": "31001A", "blue2": "31001E", "blue3": "", "bluesit": "", "redscore": 29, "bluescore": 27, "scored": 1, "scheduled": "1970-01-01T00:00:00+00:00"}, {"sku": "RE-VRC-19-0458", "division": "Division 1", "round": 4, "instance": 2, "matchnum": 1, "field": "", "red1": "71610A", "red2": "71610B", "red3": "", "redsit": "", "blue1": "61538E", "blue2": "2036D", "blue3": "", "bluesit": "", "redscore": 30, "bluescore": 14, "scored": 1, "scheduled": "1970-01-01T00:00:00+00:00"}, {"sku": "RE-VRC-19-0458", "division": "Division 1", "round": 5, "instance": 1, "matchnum": 1, "field": "", "red1": "2036B", "red2": "2036A", "red3": "", "redsit": "", "blue1": "71610A", "blue2": "71610B", "blue3": "", "bluesit": "", "redscore": 26, "bluescore": 32, "scored": 1, "scheduled": "1970-01-01T00:00:00+00:00"}, {"sku": "RE-VRC-19-9533", "division": "Division 1", "round": 2, "instance": 1, "matchnum": 8, "field": "Aero-Tech", "red1": "66617C", "red2": "71610Y", "red3": "", "redsit": "", "blue1": "71610A", "blue2": "61538C", "blue3": "", "bluesit": "", "redscore": 24, "bluescore": 15, "scored": 1, "scheduled": "2020-01-10T15:43:00+00:00"}, {"sku": "RE-VRC-19-9533", "division": "Division 1", "round": 2, "instance": 1, "matchnum": 13, "field": "Trinity Precision", "red1": "71610A", "red2": "67210K", "red3": "", "redsit": "", "blue1": "25918A", "blue2": "2036C", "blue3": "", "bluesit": "", "redscore": 9, "bluescore": 9, "scored": 1, "scheduled": "2020-01-10T16:03:00+00:00"}, {"sku": "RE-VRC-19-9533", "division": "Division 1", "round": 2, "instance": 1, "matchnum": 18, "field": "Aero-Tech", "red1": "61538A", "red2": "71610A", "red3": "", "redsit": "", "blue1": "1304X", "blue2": "71610B", "blue3": "", "bluesit": "", "redscore": 20, "bluescore": 10, "scored": 1, "scheduled": "2020-01-10T16:23:00+00:00"}, {"sku": "RE-VRC-19-9533", "division": "Division 1", "round": 2, "instance": 1, "matchnum": 27, "field": "Trinity Precision", "red1": "61538E", "red2": "71610A", "red3": "", "redsit": "", "blue1": "71610C", "blue2": "31001D", "blue3": "", "bluesit": "", "redscore": 36, "bluescore": 4, "scored": 1, "scheduled": "2020-01-10T16:59:00+00:00"}, {"sku": "RE-VRC-19-9533", "division": "Division 1", "round": 2, "instance": 1, "matchnum": 38, "field": "Aero-Tech", "red1": "61538B", "red2": "25900B", "red3": "", "redsit": "", "blue1": "71610A", "blue2": "67210A", "blue3": "", "bluesit": "", "redscore": 6, "bluescore": 17, "scored": 1, "scheduled": "2020-01-10T17:43:00+00:00"}, {"sku": "RE-VRC-19-9533", "division": "Division 1", "round": 2, "instance": 1, "matchnum": 44, "field": "Aero-Tech", "red1": "31001E", "red2": "31001B", "red3": "", "redsit": "", "blue1": "67210J", "blue2": "71610A", "blue3": "", "bluesit": "", "redscore": 8, "bluescore": 30, "scored": 1, "scheduled": "2020-01-10T19:04:00+00:00"}, {"sku": "RE-VRC-19-9533", "division": "Division 1", "round": 6, "instance": 3, "matchnum": 1, "field": "Aero-Tech", "red1": "71610A", "red2": "61538E", "red3": "", "redsit": "", "blue1": "71610X", "blue2": "25918A", "blue3": "", "bluesit": "", "redscore": 14, "bluescore": 0, "scored": 1, "scheduled": "1970-01-01T00:00:00+00:00"}, {"sku": "RE-VRC-19-9533", "division": "Division 1", "round": 3, "instance": 2, "matchnum": 1, "field": "", "red1": "71610A", "red2": "61538E", "red3": "", "redsit": "", "blue1": "67212A", "blue2": "25900A", "blue3": "", "bluesit": "", "redscore": 33, "bluescore": 30, "scored": 1, "scheduled": "1970-01-01T00:00:00+00:00"}, {"sku": "RE-VRC-19-9533", "division": "Division 1", "round": 4, "instance": 1, "matchnum": 1, "field": "", "red1": "66617C", "red2": "2036B", "red3": "", "redsit": "", "blue1": "71610A", "blue2": "61538E", "blue3": "", "bluesit": "", "redscore": 14, "bluescore": 29, "scored": 1, "scheduled": "1970-01-01T00:00:00+00:00"}, {"sku": "RE-VRC-19-9533", "division": "Division 1", "round": 5, "instance": 1, "matchnum": 1, "field": "", "red1": "71610A", "red2": "61538E", "red3": "", "redsit": "", "blue1": "2036E", "blue2": "2036A", "blue3": "", "bluesit": "", "redscore": 5, "bluescore": 38, "scored": 1, "scheduled": "1970-01-01T00:00:00+00:00"}, {"sku": "RE-VRC-19-8128", "division": "Division 1", "round": 2, "instance": 1, "matchnum": 3, "field": "Field 1", "red1": "25900B", "red2": "71610A", "red3": "", "redsit": "", "blue1": "67206E", "blue2": "67206B", "blue3": "", "bluesit": "", "redscore": 11, "bluescore": 10, "scored": 1, "scheduled": "2019-11-22T15:09:00+00:00"}, {"sku": "RE-VRC-19-8128", "division": "Division 1", "round": 2, "instance": 1, "matchnum": 14, "field": "Field 2", "red1": "61538D", "red2": "2036C", "red3": "", "redsit": "", "blue1": "71610A", "blue2": "71610Y", "blue3": "", "bluesit": "", "redscore": 24, "bluescore": 3, "scored": 1, "scheduled": "2019-11-22T15:58:30+00:00"}, {"sku": "RE-VRC-19-8128", "division": "Division 1", "round": 2, "instance": 1, "matchnum": 30, "field": "Field 2", "red1": "2036A", "red2": "71610A", "red3": "", "redsit": "", "blue1": "26000C", "blue2": "26000B", "blue3": "", "bluesit": "", "redscore": 32, "bluescore": 6, "scored": 1, "scheduled": "2019-11-22T17:10:30+00:00"}, {"sku": "RE-VRC-19-8128", "division": "Division 1", "round": 2, "instance": 1, "matchnum": 38, "field": "Field 2", "red1": "71610B", "red2": "67206D", "red3": "", "redsit": "", "blue1": "71610A", "blue2": "61526A", "blue3": "", "bluesit": "", "redscore": 7, "bluescore": 12, "scored": 1, "scheduled": "2019-11-22T17:46:30+00:00"}, {"sku": "RE-VRC-19-8128", "division": "Division 1", "round": 2, "instance": 1, "matchnum": 47, "field": "Field 1", "red1": "26000G", "red2": "2036E", "red3": "", "redsit": "", "blue1": "67211A", "blue2": "71610A", "blue3": "", "bluesit": "", "redscore": 8, "bluescore": 9, "scored": 1, "scheduled": "2019-11-22T19:27:00+00:00"}, {"sku": "RE-VRC-19-8128", "division": "Division 1", "round": 2, "instance": 1, "matchnum": 60, "field": "Field 2", "red1": "71610A", "red2": "67210A", "red3": "", "redsit": "", "blue1": "61538E", "blue2": "67211B", "blue3": "", "bluesit": "", "redscore": 13, "bluescore": 15, "scored": 1, "scheduled": "2019-11-22T20:25:30+00:00"}, {"sku": "RE-VRC-19-8128", "division": "Division 1", "round": 6, "instance": 8, "matchnum": 1, "field": "", "red1": "71610Y", "red2": "71610A", "red3": "", "redsit": "", "blue1": "61526A", "blue2": "67206C", "blue3": "", "bluesit": "", "redscore": 41, "bluescore": 3, "scored": 1, "scheduled": "1970-01-01T00:00:00+00:00"}, {"sku": "RE-VRC-19-8128", "division": "Division 1", "round": 3, "instance": 4, "matchnum": 1, "field": "", "red1": "67206D", "red2": "2036C", "red3": "", "redsit": "", "blue1": "71610Y", "blue2": "71610A", "blue3": "", "bluesit": "", "redscore": 9, "bluescore": 19, "scored": 1, "scheduled": "1970-01-01T00:00:00+00:00"}, {"sku": "RE-VRC-19-8128", "division": "Division 1", "round": 4, "instance": 2, "matchnum": 1, "field": "", "red1": "2036B", "red2": "2036A", "red3": "", "redsit": "", "blue1": "71610Y", "blue2": "71610A", "blue3": "", "bluesit": "", "redscore": 34, "bluescore": 31, "scored": 1, "scheduled": "1970-01-01T00:00:00+00:00"}, {"sku": "RE-VRC-19-9032", "division": "Division 1", "round": 2, "instance": 1, "matchnum": 1, "field": "Field 1", "red1": "67210A", "red2": "71610Y", "red3": "", "redsit": "", "blue1": "2036D", "blue2": "71610A", "blue3": "", "bluesit": "", "redscore": 2, "bluescore": 10, "scored": 1, "scheduled": "2019-11-02T14:20:00+00:00"}, {"sku": "RE-VRC-19-9032", "division": "Division 1", "round": 2, "instance": 1, "matchnum": 8, "field": "Field 2", "red1": "71610A", "red2": "61538E", "red3": "", "redsit": "", "blue1": "61538D", "blue2": "66617C", "blue3": "", "bluesit": "", "redscore": 14, "bluescore": 3, "scored": 1, "scheduled": "2019-11-02T15:02:00+00:00"}, {"sku": "RE-VRC-19-9032", "division": "Division 1", "round": 2, "instance": 1, "matchnum": 18, "field": "Field 2", "red1": "71610C", "red2": "2036A", "red3": "", "redsit": "", "blue1": "26000B", "blue2": "71610A", "blue3": "", "bluesit": "", "redscore": 18, "bluescore": 26, "scored": 1, "scheduled": "2019-11-02T15:57:30+00:00"}, {"sku": "RE-VRC-19-9032", "division": "Division 1", "round": 2, "instance": 1, "matchnum": 24, "field": "Field 2", "red1": "1304X", "red2": "71610A", "red3": "", "redsit": "", "blue1": "26000F", "blue2": "26000A", "blue3": "", "bluesit": "", "redscore": 13, "bluescore": 5, "scored": 1, "scheduled": "2019-11-02T16:30:30+00:00"}, {"sku": "RE-VRC-19-9032", "division": "Division 1", "round": 2, "instance": 1, "matchnum": 29, "field": "Field 1", "red1": "71610A", "red2": "1304X", "red3": "", "redsit": "", "blue1": "67210F", "blue2": "61538B", "blue3": "", "bluesit": "", "redscore": 11, "bluescore": 5, "scored": 1, "scheduled": "2019-11-02T18:11:00+00:00"}, {"sku": "RE-VRC-19-9032", "division": "Division 1", "round": 2, "instance": 1, "matchnum": 35, "field": "Field 1", "red1": "26000C", "red2": "71610A", "red3": "", "redsit": "", "blue1": "2036C", "blue2": "67210J", "blue3": "", "bluesit": "", "redscore": 15, "bluescore": 15, "scored": 1, "scheduled": "2019-11-02T18:44:00+00:00"}, {"sku": "RE-VRC-19-9032", "division": "Division 1", "round": 3, "instance": 3, "matchnum": 1, "field": "", "red1": "71610A", "red2": "71610C", "red3": "", "redsit": "", "blue1": "26000F", "blue2": "26000C", "blue3": "", "bluesit": "", "redscore": 18, "bluescore": 4, "scored": 1, "scheduled": "1970-01-01T00:00:00+00:00"}, {"sku": "RE-VRC-19-9032", "division": "Division 1", "round": 4, "instance": 2, "matchnum": 1, "field": "", "red1": "71610A", "red2": "71610C", "red3": "", "redsit": "", "blue1": "26000B", "blue2": "2036C", "blue3": "", "bluesit": "", "redscore": 9, "bluescore": 16, "scored": 1, "scheduled": "1970-01-01T00:00:00+00:00"}, {"sku": "RE-VRC-18-6399", "division": "Results", "round": 2, "instance": 1, "matchnum": 8, "field": "Red Field 2", "red1": "71610A", "red2": "67101D", "red3": "", "redsit": "", "blue1": "52800A", "blue2": "46838C", "blue3": "", "bluesit": "", "redscore": 8, "bluescore": 19, "scored": 1, "scheduled": "2019-04-05T14:23:00+00:00"}, {"sku": "RE-VRC-18-6399", "division": "Results", "round": 2, "instance": 1, "matchnum": 23, "field": "Red Field 1", "red1": "67210X", "red2": "71610A", "red3": "", "redsit": "", "blue1": "8193B", "blue2": "63953A", "blue3": "", "bluesit": "", "redscore": 20, "bluescore": 9, "scored": 1, "scheduled": "2019-04-05T15:23:00+00:00"}, {"sku": "RE-VRC-18-6399", "division": "Results", "round": 2, "instance": 1, "matchnum": 35, "field": "Red Field 1", "red1": "70565A", "red2": "8193C", "red3": "", "redsit": "", "blue1": "7998A", "blue2": "71610A", "blue3": "", "bluesit": "", "redscore": 26, "bluescore": 8, "scored": 1, "scheduled": "2019-04-05T16:11:00+00:00"}, {"sku": "RE-VRC-18-6399", "division": "Results", "round": 2, "instance": 1, "matchnum": 56, "field": "Red Field 2", "red1": "488A", "red2": "7786A", "red3": "", "redsit": "", "blue1": "71610A", "blue2": "9393G", "blue3": "", "bluesit": "", "redscore": 23, "bluescore": 2, "scored": 1, "scheduled": "2019-04-05T18:30:00+00:00"}, {"sku": "RE-VRC-18-6399", "division": "Results", "round": 2, "instance": 1, "matchnum": 67, "field": "Red Field 1", "red1": "71610A", "red2": "41843A", "red3": "", "redsit": "", "blue1": "33339A", "blue2": "83009H", "blue3": "", "bluesit": "", "redscore": 14, "bluescore": 16, "scored": 1, "scheduled": "2019-04-05T19:14:00+00:00"}, {"sku": "RE-VRC-18-6399", "division": "Results", "round": 2, "instance": 1, "matchnum": 85, "field": "Red Field 1", "red1": "71610X", "red2": "371T", "red3": "", "redsit": "", "blue1": "71610A", "blue2": "2882R", "blue3": "", "bluesit": "", "redscore": 28, "bluescore": 10, "scored": 1, "scheduled": "2019-04-05T20:26:00+00:00"}, {"sku": "RE-VRC-18-6399", "division": "Results", "round": 2, "instance": 1, "matchnum": 100, "field": "Red Field 2", "red1": "7903A", "red2": "8193D", "red3": "", "redsit": "", "blue1": "71610A", "blue2": "8108D", "blue3": "", "bluesit": "", "redscore": 15, "bluescore": 17, "scored": 1, "scheduled": "2019-04-05T21:26:00+00:00"}, {"sku": "RE-VRC-18-6399", "division": "Results", "round": 2, "instance": 1, "matchnum": 117, "field": "Red Field 1", "red1": "13800V", "red2": "26000C", "red3": "", "redsit": "", "blue1": "71610A", "blue2": "63953B", "blue3": "", "bluesit": "", "redscore": 23, "bluescore": 2, "scored": 1, "scheduled": "2019-04-05T22:34:00+00:00"}, {"sku": "RE-VRC-18-6399", "division": "Results", "round": 2, "instance": 1, "matchnum": 148, "field": "Red Field 2", "red1": "388A", "red2": "71610A", "red3": "", "redsit": "", "blue1": "30526D", "blue2": "18190C", "blue3": "", "bluesit": "", "redscore": 11, "bluescore": 14, "scored": 1, "scheduled": "2019-04-06T15:21:10+00:00"}, {"sku": "RE-VRC-18-6399", "division": "Results", "round": 2, "instance": 1, "matchnum": 164, "field": "Red Field 2", "red1": "71610A", "red2": "1028Y", "red3": "", "redsit": "", "blue1": "369A", "blue2": "13800X", "blue3": "", "bluesit": "", "redscore": 6, "bluescore": 30, "scored": 1, "scheduled": "2019-04-06T16:22:30+00:00"}, {"sku": "RE-VRC-19-6927", "division": "Division 1", "round": 2, "instance": 1, "matchnum": 5, "field": "Field 1", "red1": "71610X", "red2": "61538D", "red3": "", "redsit": "", "blue1": "71610A", "blue2": "2036C", "blue3": "", "bluesit": "", "redscore": 4, "bluescore": 25, "scored": 1, "scheduled": "2019-03-01T16:18:00+00:00"}, {"sku": "RE-VRC-19-6927", "division": "Division 1", "round": 2, "instance": 1, "matchnum": 10, "field": "Field 2", "red1": "71610A", "red2": "67210A", "red3": "", "redsit": "", "blue1": "26000D", "blue2": "71610B", "blue3": "", "bluesit": "", "redscore": 12, "bluescore": 13, "scored": 1, "scheduled": "2019-03-01T16:40:30+00:00"}, {"sku": "RE-VRC-19-6927", "division": "Division 1", "round": 2, "instance": 1, "matchnum": 13, "field": "Field 1", "red1": "71610A", "red2": "2036B", "red3": "", "redsit": "", "blue1": "71610C", "blue2": "31001E", "blue3": "", "bluesit": "", "redscore": 24, "bluescore": 8, "scored": 1, "scheduled": "2019-03-01T16:54:00+00:00"}, {"sku": "RE-VRC-19-6927", "division": "Division 1", "round": 2, "instance": 1, "matchnum": 20, "field": "Field 2", "red1": "61538B", "red2": "2036A", "red3": "", "redsit": "", "blue1": "31001A", "blue2": "71610A", "blue3": "", "bluesit": "", "redscore": 17, "bluescore": 19, "scored": 1, "scheduled": "2019-03-01T17:25:30+00:00"}, {"sku": "RE-VRC-19-6927", "division": "Division 1", "round": 2, "instance": 1, "matchnum": 28, "field": "Field 2", "red1": "71610A", "red2": "66617B", "red3": "", "redsit": "", "blue1": "67101C", "blue2": "26000C", "blue3": "", "bluesit": "", "redscore": 6, "bluescore": 25, "scored": 1, "scheduled": "2019-03-01T19:15:00+00:00"}, {"sku": "RE-VRC-19-6927", "division": "Division 1", "round": 2, "instance": 1, "matchnum": 33, "field": "Field 1", "red1": "25918G", "red2": "31001B", "red3": "", "redsit": "", "blue1": "67210X", "blue2": "71610A", "blue3": "", "bluesit": "", "redscore": 17, "bluescore": 9, "scored": 1, "scheduled": "2019-03-01T19:35:00+00:00"}, {"sku": "RE-VRC-19-6927", "division": "Division 1", "round": 3, "instance": 3, "matchnum": 1, "field": "", "red1": "61538A", "red2": "2036A", "red3": "", "redsit": "", "blue1": "31001A", "blue2": "71610A", "blue3": "", "bluesit": "", "redscore": 17, "bluescore": 11, "scored": 1, "scheduled": "1970-01-01T00:00:00+00:00"}, {"sku": "RE-VRC-18-5867", "division": "Division 1", "round": 2, "instance": 1, "matchnum": 2, "field": "Field 2", "red1": "2036A", "red2": "71610A", "red3": "", "redsit": "", "blue1": "31001F", "blue2": "26000B", "blue3": "", "bluesit": "", "redscore": 22, "bluescore": 8, "scored": 1, "scheduled": "2019-02-02T15:34:30+00:00"}, {"sku": "RE-VRC-18-5867", "division": "Division 1", "round": 2, "instance": 1, "matchnum": 19, "field": "Field 1", "red1": "25918A", "red2": "26000A", "red3": "", "redsit": "", "blue1": "2036D", "blue2": "71610A", "blue3": "", "bluesit": "", "redscore": 14, "bluescore": 14, "scored": 1, "scheduled": "2019-02-02T16:51:00+00:00"}, {"sku": "RE-VRC-18-5867", "division": "Division 1", "round": 2, "instance": 1, "matchnum": 24, "field": "Field 2", "red1": "71610A", "red2": "71610X", "red3": "", "redsit": "", "blue1": "20468C", "blue2": "1073G", "blue3": "", "bluesit": "", "redscore": 20, "bluescore": 11, "scored": 1, "scheduled": "2019-02-02T17:13:30+00:00"}, {"sku": "RE-VRC-18-5867", "division": "Division 1", "round": 2, "instance": 1, "matchnum": 36, "field": "Field 2", "red1": "25918G", "red2": "26000D", "red3": "", "redsit": "", "blue1": "71610A", "blue2": "2601A", "blue3": "", "bluesit": "", "redscore": 11, "bluescore": 14, "scored": 1, "scheduled": "2019-02-02T19:07:30+00:00"}, {"sku": "RE-VRC-18-5867", "division": "Division 1", "round": 2, "instance": 1, "matchnum": 45, "field": "Field 1", "red1": "71610B", "red2": "67210X", "red3": "", "redsit": "", "blue1": "61538D", "blue2": "71610A", "blue3": "", "bluesit": "", "redscore": 13, "bluescore": 12, "scored": 1, "scheduled": "2019-02-02T19:48:00+00:00"}, {"sku": "RE-VRC-18-5867", "division": "Division 1", "round": 2, "instance": 1, "matchnum": 56, "field": "Field 2", "red1": "71610A", "red2": "66617A", "red3": "", "redsit": "", "blue1": "1073A", "blue2": "61538C", "blue3": "", "bluesit": "", "redscore": 17, "bluescore": 5, "scored": 1, "scheduled": "2019-02-02T20:37:30+00:00"}, {"sku": "RE-VRC-18-5867", "division": "Division 1", "round": 3, "instance": 3, "matchnum": 1, "field": "Field 1", "red1": "2036C", "red2": "31001B", "red3": "", "redsit": "", "blue1": "71610A", "blue2": "71610C", "blue3": "", "bluesit": "", "redscore": 10, "bluescore": 15, "scored": 1, "scheduled": "1970-01-01T00:00:00+00:00"}, {"sku": "RE-VRC-18-5867", "division": "Division 1", "round": 4, "instance": 2, "matchnum": 1, "field": "", "red1": "71610A", "red2": "71610C", "red3": "", "redsit": "", "blue1": "25918G", "blue2": "26000D", "blue3": "", "bluesit": "", "redscore": 11, "bluescore": 17, "scored": 1, "scheduled": "1970-01-01T00:00:00+00:00"}, {"sku": "RE-VRC-18-6858", "division": "Division 1", "round": 2, "instance": 1, "matchnum": 3, "field": "Field 1", "red1": "26000D", "red2": "71610A", "red3": "", "redsit": "", "blue1": "7862T", "blue2": "25918A", "blue3": "", "bluesit": "", "redscore": 17, "bluescore": 16, "scored": 1, "scheduled": "2018-12-18T15:23:00+00:00"}, {"sku": "RE-VRC-18-6858", "division": "Division 1", "round": 2, "instance": 1, "matchnum": 19, "field": "Field 1", "red1": "71610X", "red2": "68688C", "red3": "", "redsit": "", "blue1": "71610A", "blue2": "7862C", "blue3": "", "bluesit": "", "redscore": 7, "bluescore": 28, "scored": 1, "scheduled": "2018-12-18T16:27:00+00:00"}, {"sku": "RE-VRC-18-6858", "division": "Division 1", "round": 2, "instance": 1, "matchnum": 25, "field": "Field 1", "red1": "26000C", "red2": "71610A", "red3": "", "redsit": "", "blue1": "7862P", "blue2": "67101D", "blue3": "", "bluesit": "", "redscore": 17, "bluescore": 19, "scored": 1, "scheduled": "2018-12-18T16:51:00+00:00"}, {"sku": "RE-VRC-18-6858", "division": "Division 1", "round": 2, "instance": 1, "matchnum": 36, "field": "Field 2", "red1": "71610A", "red2": "17771W", "red3": "", "redsit": "", "blue1": "17771Z", "blue2": "67210Y", "blue3": "", "bluesit": "", "redscore": 22, "bluescore": 7, "scored": 1, "scheduled": "2018-12-18T17:35:00+00:00"}, {"sku": "RE-VRC-18-6858", "division": "Division 1", "round": 2, "instance": 1, "matchnum": 45, "field": "Field 1", "red1": "7862W", "red2": "67210A", "red3": "", "redsit": "", "blue1": "2036A", "blue2": "71610A", "blue3": "", "bluesit": "", "redscore": 5, "bluescore": 24, "scored": 1, "scheduled": "2018-12-18T19:08:00+00:00"}, {"sku": "RE-VRC-18-6858", "division": "Division 1", "round": 2, "instance": 1, "matchnum": 51, "field": "Field 1", "red1": "31001D", "red2": "7862H", "red3": "", "redsit": "", "blue1": "26000E", "blue2": "71610A", "blue3": "", "bluesit": "", "redscore": 14, "bluescore": 8, "scored": 1, "scheduled": "2018-12-18T19:32:00+00:00"}, {"sku": "RE-VRC-18-6858", "division": "Division 1", "round": 3, "instance": 2, "matchnum": 1, "field": "", "red1": "2036C", "red2": "2036A", "red3": "", "redsit": "", "blue1": "71610A", "blue2": "71610C", "blue3": "", "bluesit": "", "redscore": 18, "bluescore": 10, "scored": 1, "scheduled": "1970-01-01T00:00:00+00:00"}, {"sku": "RE-VRC-18-6533", "division": "Division 1", "round": 2, "instance": 1, "matchnum": 7, "field": "Field 1", "red1": "2601B", "red2": "67211A", "red3": "", "redsit": "", "blue1": "71610A", "blue2": "25918G", "blue3": "", "bluesit": "", "redscore": 1, "bluescore": 14, "scored": 1, "scheduled": "2018-11-16T15:30:00+00:00"}, {"sku": "RE-VRC-18-6533", "division": "Division 1", "round": 2, "instance": 1, "matchnum": 10, "field": "Field 2", "red1": "71610A", "red2": "31001D", "red3": "", "redsit": "", "blue1": "67211B", "blue2": "71610B", "blue3": "", "bluesit": "", "redscore": 11, "bluescore": 10, "scored": 1, "scheduled": "2018-11-16T15:45:00+00:00"}, {"sku": "RE-VRC-18-6533", "division": "Division 1", "round": 2, "instance": 1, "matchnum": 15, "field": "Field 1", "red1": "26000C", "red2": "2036B", "red3": "", "redsit": "", "blue1": "71610A", "blue2": "26000A", "blue3": "", "bluesit": "", "redscore": 11, "bluescore": 4, "scored": 1, "scheduled": "2018-11-16T16:10:00+00:00"}, {"sku": "RE-VRC-18-6533", "division": "Division 1", "round": 2, "instance": 1, "matchnum": 23, "field": "Field 1", "red1": "71610A", "red2": "71610C", "red3": "", "redsit": "", "blue1": "31001A", "blue2": "61526C", "blue3": "", "bluesit": "", "redscore": 14, "bluescore": 10, "scored": 1, "scheduled": "2018-11-16T16:50:00+00:00"}, {"sku": "RE-VRC-18-6533", "division": "Division 1", "round": 2, "instance": 1, "matchnum": 31, "field": "Field 1", "red1": "2036A", "red2": "31001E", "red3": "", "redsit": "", "blue1": "61526B", "blue2": "71610A", "blue3": "", "bluesit": "", "redscore": 17, "bluescore": 3, "scored": 1, "scheduled": "2018-11-16T17:30:00+00:00"}, {"sku": "RE-VRC-18-6533", "division": "Division 1", "round": 2, "instance": 1, "matchnum": 37, "field": "Field 1", "red1": "26000B", "red2": "71610A", "red3": "", "redsit": "", "blue1": "61526A", "blue2": "2601A", "blue3": "", "bluesit": "", "redscore": 19, "bluescore": 2, "scored": 1, "scheduled": "2018-11-16T19:00:00+00:00"}, {"sku": "RE-VRC-18-6533", "division": "Division 1", "round": 3, "instance": 4, "matchnum": 1, "field": "", "red1": "71610A", "red2": "71610C", "red3": "", "redsit": "", "blue1": "2036A", "blue2": "2036D", "blue3": "", "bluesit": "", "redscore": 13, "bluescore": 5, "scored": 1, "scheduled": "1970-01-01T00:00:00+00:00"}, {"sku": "RE-VRC-18-6533", "division": "Division 1", "round": 4, "instance": 2, "matchnum": 1, "field": "", "red1": "25918G", "red2": "61526B", "red3": "", "redsit": "", "blue1": "71610A", "blue2": "71610C", "blue3": "", "bluesit": "", "redscore": 5, "bluescore": 10, "scored": 1, "scheduled": "1970-01-01T00:00:00+00:00"}, {"sku": "RE-VRC-18-6533", "division": "Division 1", "round": 5, "instance": 1, "matchnum": 1, "field": "", "red1": "2036C", "red2": "26000C", "red3": "", "redsit": "", "blue1": "71610A", "blue2": "71610C", "blue3": "", "bluesit": "", "redscore": 8, "bluescore": 10, "scored": 1, "scheduled": "1970-01-01T00:00:00+00:00"}, {"sku": "RE-VRC-18-5726", "division": "Division 1", "round": 2, "instance": 1, "matchnum": 2, "field": "Field 2", "red1": "26000C", "red2": "71610A", "red3": "", "redsit": "", "blue1": "61538A", "blue2": "26000B", "blue3": "", "bluesit": "", "redscore": 16, "bluescore": 7, "scored": 1, "scheduled": "2018-10-30T15:06:30+00:00"}, {"sku": "RE-VRC-18-5726", "division": "Division 1", "round": 2, "instance": 1, "matchnum": 11, "field": "Field 1", "red1": "71610A", "red2": "2036A", "red3": "", "redsit": "", "blue1": "2036B", "blue2": "71610C", "blue3": "", "bluesit": "", "redscore": 19, "bluescore": 9, "scored": 1, "scheduled": "2018-10-30T16:00:00+00:00"}, {"sku": "RE-VRC-18-5726", "division": "Division 1", "round": 2, "instance": 1, "matchnum": 15, "field": "Field 1", "red1": "71610B", "red2": "31001F", "red3": "", "redsit": "", "blue1": "71610A", "blue2": "61538E", "blue3": "", "bluesit": "", "redscore": 12, "bluescore": 18, "scored": 1, "scheduled": "2018-10-30T16:24:00+00:00"}, {"sku": "RE-VRC-18-5726", "division": "Division 1", "round": 2, "instance": 1, "matchnum": 21, "field": "Field 1", "red1": "26000E", "red2": "61538B", "red3": "", "redsit": "", "blue1": "31001E", "blue2": "71610A", "blue3": "", "bluesit": "", "redscore": 5, "bluescore": 15, "scored": 1, "scheduled": "2018-10-30T17:00:00+00:00"}, {"sku": "RE-VRC-18-5726", "division": "Division 1", "round": 2, "instance": 1, "matchnum": 28, "field": "Field 2", "red1": "26000D", "red2": "67210A", "red3": "", "redsit": "", "blue1": "2036D", "blue2": "71610A", "blue3": "", "bluesit": "", "redscore": 10, "bluescore": 12, "scored": 1, "scheduled": "2018-10-30T18:39:00+00:00"}, {"sku": "RE-VRC-18-5726", "division": "Division 1", "round": 2, "instance": 1, "matchnum": 32, "field": "Field 2", "red1": "71610A", "red2": "67210X", "red3": "", "redsit": "", "blue1": "30080A", "blue2": "61538D", "blue3": "", "bluesit": "", "redscore": 22, "bluescore": 10, "scored": 1, "scheduled": "2018-10-30T19:03:00+00:00"}, {"sku": "RE-VRC-18-5726", "division": "Division 1", "round": 3, "instance": 1, "matchnum": 1, "field": "", "red1": "71610A", "red2": "67210X", "red3": "", "redsit": "", "blue1": "26000D", "blue2": "2036D", "blue3": "", "bluesit": "", "redscore": 26, "bluescore": 4, "scored": 1, "scheduled": "1970-01-01T00:00:00+00:00"}, {"sku": "RE-VRC-18-5726", "division": "Division 1", "round": 4, "instance": 1, "matchnum": 1, "field": "", "red1": "71610A", "red2": "67210X", "red3": "", "redsit": "", "blue1": "2036A", "blue2": "2036C", "blue3": "", "bluesit": "", "redscore": 13, "bluescore": 9, "scored": 1, "scheduled": "1970-01-01T00:00:00+00:00"}, {"sku": "RE-VRC-18-5726", "division": "Division 1", "round": 5, "instance": 1, "matchnum": 1, "field": "", "red1": "71610A", "red2": "67210X", "red3": "", "redsit": "", "blue1": "71610X", "blue2": "61538A", "blue3": "", "bluesit": "", "redscore": 17, "bluescore": 10, "scored": 1, "scheduled": "1970-01-01T00:00:00+00:00"}, {"sku": "RE-VRC-17-4565", "division": "Division 1", "round": 2, "instance": 1, "matchnum": 8, "field": "Field 2", "red1": "190C", "red2": "2036A", "red3": "", "redsit": "", "blue1": "71610A", "blue2": "67210W", "blue3": "", "bluesit": "", "redscore": 22, "bluescore": 12, "scored": 1, "scheduled": "2018-02-24T15:49:15+00:00"}, {"sku": "RE-VRC-17-4565", "division": "Division 1", "round": 2, "instance": 1, "matchnum": 14, "field": "Field 2", "red1": "4101J", "red2": "7862Z", "red3": "", "redsit": "", "blue1": "66725A", "blue2": "71610A", "blue3": "", "bluesit": "", "redscore": 93, "bluescore": 7, "scored": 1, "scheduled": "2018-02-24T16:05:45+00:00"}, {"sku": "RE-VRC-17-4565", "division": "Division 1", "round": 2, "instance": 1, "matchnum": 27, "field": "Field 1", "red1": "96396D", "red2": "71610A", "red3": "", "redsit": "", "blue1": "55666K", "blue2": "67210A", "blue3": "", "bluesit": "", "redscore": 14, "bluescore": 16, "scored": 1, "scheduled": "2018-02-24T16:41:30+00:00"}, {"sku": "RE-VRC-17-4565", "division": "Division 1", "round": 2, "instance": 1, "matchnum": 42, "field": "Field 2", "red1": "71610A", "red2": "50027C", "red3": "", "redsit": "", "blue1": "7862P", "blue2": "7862V", "blue3": "", "bluesit": "", "redscore": 15, "bluescore": 49, "scored": 1, "scheduled": "2018-02-24T17:22:45+00:00"}, {"sku": "RE-VRC-17-4565", "division": "Division 1", "round": 2, "instance": 1, "matchnum": 50, "field": "Field 2", "red1": "190X", "red2": "7862D", "red3": "", "redsit": "", "blue1": "7862R", "blue2": "71610A", "blue3": "", "bluesit": "", "redscore": 79, "bluescore": 87, "scored": 1, "scheduled": "2018-02-24T17:44:45+00:00"}, {"sku": "RE-VRC-17-4565", "division": "Division 1", "round": 2, "instance": 1, "matchnum": 66, "field": "Field 2", "red1": "71610A", "red2": "26000B", "red3": "", "redsit": "", "blue1": "7862F", "blue2": "71610C", "blue3": "", "bluesit": "", "redscore": 22, "bluescore": 50, "scored": 1, "scheduled": "2018-02-24T19:25:00+00:00"}, {"sku": "RE-VRC-17-4565", "division": "Division 1", "round": 2, "instance": 1, "matchnum": 79, "field": "Field 1", "red1": "71610B", "red2": "26000D", "red3": "", "redsit": "", "blue1": "71610A", "blue2": "96396B", "blue3": "", "bluesit": "", "redscore": 5, "bluescore": 45, "scored": 1, "scheduled": "2018-02-24T19:57:30+00:00"}, {"sku": "RE-VRC-17-4085", "division": "Division 1", "round": 2, "instance": 1, "matchnum": 4, "field": "Field 2", "red1": "4101J", "red2": "47511A", "red3": "", "redsit": "", "blue1": "15352E", "blue2": "71610A", "blue3": "", "bluesit": "", "redscore": 69, "bluescore": 23, "scored": 1, "scheduled": "2018-01-27T16:12:45+00:00"}, {"sku": "RE-VRC-17-4085", "division": "Division 1", "round": 2, "instance": 1, "matchnum": 9, "field": "Field 1", "red1": "7862B", "red2": "71610A", "red3": "", "redsit": "", "blue1": "47511C", "blue2": "84200A", "blue3": "", "bluesit": "", "redscore": 74, "bluescore": 11, "scored": 1, "scheduled": "2018-01-27T16:34:00+00:00"}, {"sku": "RE-VRC-17-4085", "division": "Division 1", "round": 2, "instance": 1, "matchnum": 17, "field": "Field 1", "red1": "62577A", "red2": "47511B", "red3": "", "redsit": "", "blue1": "31001A", "blue2": "71610A", "blue3": "", "bluesit": "", "redscore": 29, "bluescore": 13, "scored": 1, "scheduled": "2018-01-27T17:08:00+00:00"}, {"sku": "RE-VRC-17-4085", "division": "Division 1", "round": 2, "instance": 1, "matchnum": 26, "field": "Field 2", "red1": "71610A", "red2": "13278A", "red3": "", "redsit": "", "blue1": "71610C", "blue2": "71610B", "blue3": "", "bluesit": "", "redscore": 17, "bluescore": 12, "scored": 1, "scheduled": "2018-01-27T17:46:15+00:00"}, {"sku": "RE-VRC-17-4085", "division": "Division 1", "round": 2, "instance": 1, "matchnum": 34, "field": "Field 2", "red1": "7862R", "red2": "31001B", "red3": "", "redsit": "", "blue1": "71610A", "blue2": "7862U", "blue3": "", "bluesit": "", "redscore": 50, "bluescore": 77, "scored": 1, "scheduled": "2018-01-27T19:17:00+00:00"}, {"sku": "RE-VRC-17-4085", "division": "Division 1", "round": 2, "instance": 1, "matchnum": 46, "field": "Field 2", "red1": "7232X", "red2": "71610A", "red3": "", "redsit": "", "blue1": "50027B", "blue2": "7862K", "blue3": "", "bluesit": "", "redscore": 97, "bluescore": 51, "scored": 1, "scheduled": "2018-01-27T20:08:00+00:00"}, {"sku": "RE-VRC-17-4085", "division": "Division 1", "round": 2, "instance": 1, "matchnum": 57, "field": "Field 1", "red1": "26000A", "red2": "71610A", "red3": "", "redsit": "", "blue1": "26000B", "blue2": "13278B", "blue3": "", "bluesit": "", "redscore": 11, "bluescore": 24, "scored": 1, "scheduled": "2018-01-27T20:54:45+00:00"}, {"sku": "RE-VRC-17-4085", "division": "Division 1", "round": 3, "instance": 3, "matchnum": 1, "field": "", "red1": "7232X", "red2": "7232Z", "red3": "31001D", "redsit": "31001D", "blue1": "71610A", "blue2": "71610C", "blue3": "26000B", "bluesit": "71610C", "redscore": 135, "bluescore": 33, "scored": 1, "scheduled": "1970-01-01T00:00:00+00:00"}, {"sku": "RE-VRC-17-4085", "division": "Division 1", "round": 3, "instance": 3, "matchnum": 2, "field": "", "red1": "7232X", "red2": "7232Z", "red3": "31001D", "redsit": "7232Z", "blue1": "71610A", "blue2": "71610C", "blue3": "26000B", "bluesit": "26000B", "redscore": 19, "bluescore": 2, "scored": 1, "scheduled": "1970-01-01T00:00:00+00:00"}], "rankings": [{"sku": "RE-VRC-19-9789", "division": "Division 1", "rank": 23, "team": "71610A", "wins": 1, "losses": 5, "ties": 0, "wp": 2, "ap": 0, "sp": 98, "trsp": 34, "max_score": 34, "opr": 6.89679, "dpr": 11.2353, "ccwm": -4.33855}, {"sku": "RE-VRC-19-9672", "division": "Division 1", "rank": 9, "team": "71610A", "wins": 4, "losses": 2, "ties": 0, "wp": 8, "ap": 27, "sp": 51, "trsp": 27, "max_score": 29, "opr": 6.70338, "dpr": 2.19214, "ccwm": 4.51124}, {"sku": "RE-VRC-19-0458", "division": "Division 1", "rank": 3, "team": "71610A", "wins": 5, "losses": 1, "ties": 0, "wp": 10, "ap": 27, "sp": 77, "trsp": 34, "max_score": 64, "opr": 28.0152, "dpr": 6.24882, "ccwm": 21.7664}, {"sku": "RE-VRC-19-9533", "division": "Division 1", "rank": 5, "team": "71610A", "wins": 4, "losses": 1, "ties": 1, "wp": 9, "ap": 27, "sp": 52, "trsp": 26, "max_score": 36, "opr": 16.9956, "dpr": 1.69123, "ccwm": 15.3044}, {"sku": "RE-VRC-19-8128", "division": "Division 1", "rank": 11, "team": "71610A", "wins": 4, "losses": 2, "ties": 0, "wp": 8, "ap": 21, "sp": 47, "trsp": 42, "max_score": 41, "opr": 9.2002, "dpr": 6.11417, "ccwm": 3.08603}, {"sku": "RE-VRC-19-9032", "division": "Division 1", "rank": 2, "team": "71610A", "wins": 5, "losses": 0, "ties": 1, "wp": 11, "ap": 30, "sp": 48, "trsp": 18, "max_score": 26, "opr": 8.69843, "dpr": 3.24788, "ccwm": 5.45055}, {"sku": "RE-VRC-18-6399", "division": "Results", "rank": 59, "team": "71610A", "wins": 2, "losses": 8, "ties": 0, "wp": 4, "ap": 16, "sp": 85, "trsp": 126, "max_score": 20, "opr": 2.32612, "dpr": 11.1724, "ccwm": -8.84628}, {"sku": "RE-VRC-19-6927", "division": "Division 1", "rank": 13, "team": "71610A", "wins": 3, "losses": 3, "ties": 0, "wp": 6, "ap": 12, "sp": 56, "trsp": 35, "max_score": 25, "opr": 10.6576, "dpr": 4.90014, "ccwm": 5.7575}, {"sku": "RE-VRC-18-5867", "division": "Division 1", "rank": 8, "team": "71610A", "wins": 4, "losses": 1, "ties": 1, "wp": 9, "ap": 16, "sp": 61, "trsp": 33, "max_score": 22, "opr": 10.2935, "dpr": 3.41083, "ccwm": 6.88268}, {"sku": "RE-VRC-18-6858", "division": "Division 1", "rank": 7, "team": "71610A", "wins": 4, "losses": 2, "ties": 0, "wp": 8, "ap": 12, "sp": 60, "trsp": 36, "max_score": 28, "opr": 12.7071, "dpr": 6.25952, "ccwm": 6.44759}, {"sku": "RE-VRC-18-6533", "division": "Division 1", "rank": 4, "team": "71610A", "wins": 4, "losses": 2, "ties": 0, "wp": 8, "ap": 12, "sp": 30, "trsp": 19, "max_score": 19, "opr": 7.22606, "dpr": 6.02913, "ccwm": 1.19694}, {"sku": "RE-VRC-18-5726", "division": "Division 1", "rank": 1, "team": "71610A", "wins": 6, "losses": 0, "ties": 0, "wp": 12, "ap": 24, "sp": 53, "trsp": 26, "max_score": 26, "opr": 10.3957, "dpr": 3.67463, "ccwm": 6.72103}, {"sku": "RE-VRC-17-4565", "division": "Division 1", "rank": 35, "team": "71610A", "wins": 2, "losses": 5, "ties": 0, "wp": 4, "ap": 10, "sp": 154, "trsp": 54, "max_score": 87, "opr": 8.90267, "dpr": 31.5686, "ccwm": -22.6659}, {"sku": "RE-VRC-17-4085", "division": "Division 1", "rank": 10, "team": "71610A", "wins": 4, "losses": 3, "ties": 0, "wp": 8, "ap": 30, "sp": 171, "trsp": 20, "max_score": 97, "opr": 9.50178, "dpr": 21.6484, "ccwm": -12.1467}], "season_rankings": [{"team": "71610A", "season": "Tower Takeover", "program": "VRC", "vrating_rank": 816, "vrating": 74.356495615342}, {"team": "71610A", "season": "Turning Point", "program": "VRC", "vrating_rank": 1779, "vrating": 54.822792685466}, {"team": "71610A", "season": "In The Zone", "program": "VRC", "vrating_rank": 6426, "vrating": -5.305211901041}], "awards": [{"sku": "RE-VRC-19-9789", "name": "Robot Skills Champion (VRC/VEXU)", "team": "71610A", "qualifies": [], "order": 3}, {"sku": "RE-VRC-19-9672", "name": "Tournament Finalists (VRC/VEXU)", "team": "71610A", "qualifies": [], "order": 4}, {"sku": "RE-VRC-19-0458", "name": "Excellence Award (VRC/VEXU)", "team": "71610A", "qualifies": [], "order": 0}, {"sku": "RE-VRC-19-0458", "name": "Tournament Champions (VRC/VEXU)", "team": "71610A", "qualifies": [], "order": 1}, {"sku": "RE-VRC-19-9533", "name": "Tournament Finalists (VRC/VEXU)", "team": "71610A", "qualifies": [], "order": 4}, {"sku": "RE-VRC-19-9533", "name": "Robot Skills Champion (VRC/VEXU)", "team": "71610A", "qualifies": [], "order": 5}, {"sku": "RE-VRC-19-8128", "name": "Robot Skills Champion (VRC/VEXU)", "team": "71610A", "qualifies": [], "order": 5}, {"sku": "RE-VRC-19-6927", "name": "Design Award (VRC/VEXU)", "team": "71610A", "qualifies": [], "order": 2}, {"sku": "RE-VRC-18-6858", "name": "Design Award (VRC/VEXU)", "team": "71610A", "qualifies": [], "order": 1}, {"sku": "RE-VRC-18-6533", "name": "Excellence Award (VRC/VEXU)", "team": "71610A", "qualifies": [], "order": 0}, {"sku": "RE-VRC-18-6533", "name": "Tournament Champions (VRC/VEXU)", "team": "71610A", "qualifies": [], "order": 1}, {"sku": "RE-VRC-18-5726", "name": "Excellence Award (VRC/VEXU)", "team": "71610A", "qualifies": [], "order": 0}, {"sku": "RE-VRC-18-5726", "name": "Tournament Champions (VRC/VEXU)", "team": "71610A", "qualifies": [], "order": 1}], "skills": [{"sku": "RE-VRC-19-9789", "type": 2, "rank": 1, "team": "71610A", "program": "VRC", "attempts": 6, "score": 26}, {"sku": "RE-VRC-19-9789", "type": 0, "rank": 1, "team": "71610A", "program": "VRC", "attempts": 3, "score": 24}, {"sku": "RE-VRC-19-9789", "type": 1, "rank": 1, "team": "71610A", "program": "VRC", "attempts": 3, "score": 2}, {"sku": "RE-VRC-19-9672", "type": 0, "rank": 21, "team": "71610A", "program": "VRC", "attempts": 3, "score": 3}, {"sku": "RE-VRC-19-9672", "type": 2, "rank": 21, "team": "71610A", "program": "VRC", "attempts": 3, "score": 3}, {"sku": "RE-VRC-19-9672", "type": 1, "rank": 21, "team": "71610A", "program": "VRC", "attempts": 0, "score": 0}, {"sku": "RE-VRC-19-0458", "type": 2, "rank": 2, "team": "71610A", "program": "VRC", "attempts": 4, "score": 14}, {"sku": "RE-VRC-19-0458", "type": 0, "rank": 2, "team": "71610A", "program": "VRC", "attempts": 3, "score": 10}, {"sku": "RE-VRC-19-0458", "type": 1, "rank": 2, "team": "71610A", "program": "VRC", "attempts": 1, "score": 4}, {"sku": "RE-VRC-19-9533", "type": 0, "rank": 1, "team": "71610A", "program": "VRC", "attempts": 3, "score": 20}, {"sku": "RE-VRC-19-9533", "type": 2, "rank": 1, "team": "71610A", "program": "VRC", "attempts": 6, "score": 20}, {"sku": "RE-VRC-19-9533", "type": 1, "rank": 1, "team": "71610A", "program": "VRC", "attempts": 3, "score": 0}, {"sku": "RE-VRC-19-8128", "type": 2, "rank": 1, "team": "71610A", "program": "VRC", "attempts": 6, "score": 22}, {"sku": "RE-VRC-19-8128", "type": 0, "rank": 1, "team": "71610A", "program": "VRC", "attempts": 3, "score": 20}, {"sku": "RE-VRC-19-8128", "type": 1, "rank": 1, "team": "71610A", "program": "VRC", "attempts": 3, "score": 2}, {"sku": "RE-VRC-19-9032", "type": 0, "rank": 8, "team": "71610A", "program": "VRC", "attempts": 2, "score": 4}, {"sku": "RE-VRC-19-9032", "type": 2, "rank": 8, "team": "71610A", "program": "VRC", "attempts": 2, "score": 4}, {"sku": "RE-VRC-19-9032", "type": 1, "rank": 8, "team": "71610A", "program": "VRC", "attempts": 0, "score": 0}, {"sku": "RE-VRC-18-6399", "type": 2, "rank": 87, "team": "71610A", "program": "VRC", "attempts": 1, "score": 9}, {"sku": "RE-VRC-18-6399", "type": 0, "rank": 90, "team": "71610A", "program": "VRC", "attempts": 1, "score": 9}, {"sku": "RE-VRC-18-6399", "type": 1, "rank": 90, "team": "71610A", "program": "VRC", "attempts": 0, "score": 0}, {"sku": "RE-VRC-19-6927", "type": 2, "rank": 9, "team": "71610A", "program": "VRC", "attempts": 4, "score": 13}, {"sku": "RE-VRC-19-6927", "type": 0, "rank": 9, "team": "71610A", "program": "VRC", "attempts": 2, "score": 12}, {"sku": "RE-VRC-19-6927", "type": 1, "rank": 9, "team": "71610A", "program": "VRC", "attempts": 2, "score": 1}, {"sku": "RE-VRC-18-6858", "type": 2, "rank": 10, "team": "71610A", "program": "VRC", "attempts": 3, "score": 10}, {"sku": "RE-VRC-18-6858", "type": 0, "rank": 10, "team": "71610A", "program": "VRC", "attempts": 1, "score": 7}, {"sku": "RE-VRC-18-6858", "type": 1, "rank": 10, "team": "71610A", "program": "VRC", "attempts": 2, "score": 3}, {"sku": "RE-VRC-18-6533", "type": 2, "rank": 3, "team": "71610A", "program": "VRC", "attempts": 2, "score": 9}, {"sku": "RE-VRC-18-6533", "type": 0, "rank": 3, "team": "71610A", "program": "VRC", "attempts": 1, "score": 8}, {"sku": "RE-VRC-18-6533", "type": 1, "rank": 3, "team": "71610A", "program": "VRC", "attempts": 1, "score": 1}, {"sku": "RE-VRC-18-5726", "type": 0, "rank": 3, "team": "71610A", "program": "VRC", "attempts": 3, "score": 9}, {"sku": "RE-VRC-18-5726", "type": 2, "rank": 3, "team": "71610A", "program": "VRC", "attempts": 4, "score": 9}, {"sku": "RE-VRC-18-5726", "type": 1, "rank": 3, "team": "71610A", "program": "VRC", "attempts": 1, "score": 0}]}