{"event": {"sku": "RE-VRC-18-6528", "key": "RE-VRC-18-6528", "program": "VRC", "name": "Bellarmine Bay Area VEX Robotics Tournament", "loc_venue": "Bellarmine College Preparatory", "loc_address1": "960 West Hedding Street", "loc_address2": "", "loc_city": "San Jose", "loc_region": "California", "loc_postcode": "95126", "loc_country": "United States", "season": "Turning Point", "start": "2018-11-16T00:00:00+00:00", "end": "2018-11-17T23:59:59+00:00", "divisions": ["Division 1"]}, "matches": [{"sku": "RE-VRC-18-6528", "division": "Division 1", "round": 2, "instance": 1, "matchnum": 1, "field": "Einstein", "red1": "5297D", "red2": "11101A", "red3": "", "redsit": "", "blue1": "5776X", "blue2": "88909D", "blue3": "", "bluesit": "", "redscore": 23, "bluescore": 5, "scored": 1, "scheduled": "2018-11-17T19:00:00+00:00"}, {"sku": "RE-VRC-18-6528", "division": "Division 1", "round": 2, "instance": 1, "matchnum": 2, "field": "Tesla", "red1": "43426C", "red2": "88909Y", "red3": "", "redsit": "", "blue1": "11729A", "blue2": "254D", "blue3": "", "bluesit": "", "redscore": 20, "bluescore": 5, "scored": 1, "scheduled": "2018-11-17T19:03:00+00:00"}, {"sku": "RE-VRC-18-6528", "division": "Division 1", "round": 2, "instance": 1, "matchnum": 3, "field": "Einstein", "red1": "4008A", "red2": "315R", "red3": "", "redsit": "", "blue1": "79687A", "blue2": "1868X", "blue3": "", "bluesit": "", "redscore": 24, "bluescore": 15, "scored": 1, "scheduled": "2018-11-17T19:06:00+00:00"}, {"sku": "RE-VRC-18-6528", "division": "Division 1", "round": 2, "instance": 1, "matchnum": 4, "field": "Tesla", "red1": "920A", "red2": "88909A", "red3": "", "redsit": "", "blue1": "21246D", "blue2": "5297A", "blue3": "", "bluesit": "", "redscore": 6, "bluescore": 19, "scored": 1, "scheduled": "2018-11-17T19:09:00+00:00"}, {"sku": "RE-VRC-18-6528", "division": "Division 1", "round": 2, "instance": 1, "matchnum": 5, "field": "Einstein", "red1": "37880G", "red2": "254A", "red3": "", "redsit": "", "blue1": "6374A", "blue2": "5327C", "blue3": "", "bluesit": "", "redscore": 13, "bluescore": 20, "scored": 1, "scheduled": "2018-11-17T19:12:00+00:00"}, {"sku": "RE-VRC-18-6528", "division": "Division 1", "round": 2, "instance": 1, "matchnum": 6, "field": "Tesla", "red1": "2882R", "red2": "95070D", "red3": "", "redsit": "", "blue1": "315Y", "blue2": "254X", "blue3": "", "bluesit": "", "redscore": 18, "bluescore": 14, "scored": 1, "scheduled": "2018-11-17T19:15:00+00:00"}, {"sku": "RE-VRC-18-6528", "division": "Division 1", "round": 2, "instance": 1, "matchnum": 7, "field": "Einstein", "red1": "5776E", "red2": "94927A", "red3": "", "redsit": "", "blue1": "315G", "blue2": "95070B", "blue3": "", "bluesit": "", "redscore": 11, "bluescore": 27, "scored": 1, "scheduled": "2018-11-17T19:18:00+00:00"}, {"sku": "RE-VRC-18-6528", "division": "Division 1", "round": 2, "instance": 1, "matchnum": 8, "field": "Tesla", "red1": "6374G", "red2": "95070C", "red3": "", "redsit": "", "blue1": "7916A", "blue2": "254F", "blue3": "", "bluesit": "", "redscore": 4, "bluescore": 21, "scored": 1, "scheduled": "2018-11-17T19:21:00+00:00"}, {"sku": "RE-VRC-18-6528", "division": "Division 1", "round": 2, "instance": 1, "matchnum": 9, "field": "Einstein", "red1": "1868Z", "red2": "86868R", "red3": "", "redsit": "", "blue1": "920D", "blue2": "254B", "blue3": "", "bluesit": "", "redscore": 29, "bluescore": 4, "scored": 1, "scheduled": "2018-11-17T19:24:00+00:00"}, {"sku": "RE-VRC-18-6528", "division": "Division 1", "round": 2, "instance": 1, "matchnum": 10, "field": "Tesla", "red1": "315X", "red2": "88909X", "red3": "", "redsit": "", "blue1": "5297B", "blue2": "88811A", "blue3": "", "bluesit": "", "redscore": 27, "bluescore": 7, "scored": 1, "scheduled": "2018-11-17T19:27:00+00:00"}, {"sku": "RE-VRC-18-6528", "division": "Division 1", "round": 2, "instance": 1, "matchnum": 11, "field": "Einstein", "red1": "254C", "red2": "139A", "red3": "", "redsit": "", "blue1": "5297C", "blue2": "1868A", "blue3": "", "bluesit": "", "redscore": 19, "bluescore": 4, "scored": 1, "scheduled": "2018-11-17T19:30:00+00:00"}, {"sku": "RE-VRC-18-6528", "division": "Division 1", "round": 2, "instance": 1, "matchnum": 12, "field": "Tesla", "red1": "254W", "red2": "43428A", "red3": "", "redsit": "", "blue1": "920B", "blue2": "8000B", "blue3": "", "bluesit": "", "redscore": 9, "bluescore": 8, "scored": 1, "scheduled": "2018-11-17T19:33:00+00:00"}, {"sku": "RE-VRC-18-6528", "division": "Division 1", "round": 2, "instance": 1, "matchnum": 13, "field": "Einstein", "red1": "5776T", "red2": "94065J", "red3": "", "redsit": "", "blue1": "95070A", "blue2": "6374B", "blue3": "", "bluesit": "", "redscore": 35, "bluescore": 1, "scored": 1, "scheduled": "2018-11-17T19:36:00+00:00"}, {"sku": "RE-VRC-18-6528", "division": "Division 1", "round": 2, "instance": 1, "matchnum": 14, "field": "Tesla", "red1": "920C", "red2": "43426A", "red3": "", "redsit": "", "blue1": "5776A", "blue2": "6627X", "blue3": "", "bluesit": "", "redscore": 7, "bluescore": 29, "scored": 1, "scheduled": "2018-11-17T19:39:00+00:00"}, {"sku": "RE-VRC-18-6528", "division": "Division 1", "round": 2, "instance": 1, "matchnum": 15, "field": "Einstein", "red1": "74264A", "red2": "1868K", "red3": "", "redsit": "", "blue1": "6374X", "blue2": "79687A", "blue3": "", "bluesit": "", "redscore": 19, "bluescore": 11, "scored": 1, "scheduled": "2018-11-17T19:42:00+00:00"}, {"sku": "RE-VRC-18-6528", "division": "Division 1", "round": 2, "instance": 1, "matchnum": 16, "field": "Tesla", "red1": "5327C", "red2": "920A", "red3": "", "redsit": "", "blue1": "11101A", "blue2": "2882R", "blue3": "", "bluesit": "", "redscore": 32, "bluescore": 12, "scored": 1, "scheduled": "2018-11-17T19:45:00+00:00"}, {"sku": "RE-VRC-18-6528", "division": "Division 1", "round": 2, "instance": 1, "matchnum": 17, "field": "Einstein", "red1": "88909D", "red2": "6374A", "red3": "", "redsit": "", "blue1": "1868Z", "blue2": "88909X", "blue3": "", "bluesit": "", "redscore": 9, "bluescore": 18, "scored": 1, "scheduled": "2018-11-17T19:48:00+00:00"}, {"sku": "RE-VRC-18-6528", "division": "Division 1", "round": 2, "instance": 1, "matchnum": 18, "field": "Tesla", "red1": "315Y", "red2": "1868X", "red3": "", "redsit": "", "blue1": "43426C", "blue2": "37880G", "blue3": "", "bluesit": "", "redscore": 24, "bluescore": 6, "scored": 1, "scheduled": "2018-11-17T19:51:00+00:00"}, {"sku": "RE-VRC-18-6528", "division": "Division 1", "round": 2, "instance": 1, "matchnum": 19, "field": "Einstein", "red1": "95070B", "red2": "5297A", "red3": "", "redsit": "", "blue1": "315R", "blue2": "5297C", "blue3": "", "bluesit": "", "redscore": 8, "bluescore": 25, "scored": 1, "scheduled": "2018-11-17T19:54:00+00:00"}, {"sku": "RE-VRC-18-6528", "division": "Division 1", "round": 2, "instance": 1, "matchnum": 20, "field": "Tesla", "red1": "254X", "red2": "5776X", "red3": "", "redsit": "", "blue1": "254D", "blue2": "95070A", "blue3": "", "bluesit": "", "redscore": 14, "bluescore": 14, "scored": 1, "scheduled": "2018-11-17T19:57:00+00:00"}, {"sku": "RE-VRC-18-6528", "division": "Division 1", "round": 2, "instance": 1, "matchnum": 21, "field": "Einstein", "red1": "1868A", "red2": "920C", "red3": "", "redsit": "", "blue1": "95070C", "blue2": "88909Y", "blue3": "", "bluesit": "", "redscore": 25, "bluescore": 6, "scored": 1, "scheduled": "2018-11-17T20:00:00+00:00"}, {"sku": "RE-VRC-18-6528", "division": "Division 1", "round": 2, "instance": 1, "matchnum": 22, "field": "Tesla", "red1": "94065J", "red2": "920D", "red3": "", "redsit": "", "blue1": "4008A", "blue2": "94927A", "blue3": "", "bluesit": "", "redscore": 25, "bluescore": 7, "scored": 1, "scheduled": "2018-11-17T20:03:00+00:00"}, {"sku": "RE-VRC-18-6528", "division": "Division 1", "round": 2, "instance": 1, "matchnum": 23, "field": "Einstein", "red1": "88811A", "red2": "95070D", "red3": "", "redsit": "", "blue1": "254C", "blue2": "6374G", "blue3": "", "bluesit": "", "redscore": 24, "bluescore": 4, "scored": 1, "scheduled": "2018-11-17T20:06:00+00:00"}, {"sku": "RE-VRC-18-6528", "division": "Division 1", "round": 2, "instance": 1, "matchnum": 24, "field": "Tesla", "red1": "254B", "red2": "315G", "red3": "", "redsit": "", "blue1": "5297D", "blue2": "5776A", "blue3": "", "bluesit": "", "redscore": 22, "bluescore": 5, "scored": 1, "scheduled": "2018-11-17T20:09:00+00:00"}, {"sku": "RE-VRC-18-6528", "division": "Division 1", "round": 2, "instance": 1, "matchnum": 25, "field": "Einstein", "red1": "5297B", "red2": "6627X", "red3": "", "redsit": "", "blue1": "254W", "blue2": "86868R", "blue3": "", "bluesit": "", "redscore": 21, "bluescore": 7, "scored": 1, "scheduled": "2018-11-17T20:12:00+00:00"}, {"sku": "RE-VRC-18-6528", "division": "Division 1", "round": 2, "instance": 1, "matchnum": 26, "field": "Tesla", "red1": "254F", "red2": "8000B", "red3": "", "redsit": "", "blue1": "88909A", "blue2": "74264A", "blue3": "", "bluesit": "", "redscore": 16, "bluescore": 18, "scored": 1, "scheduled": "2018-11-17T20:15:00+00:00"}, {"sku": "RE-VRC-18-6528", "division": "Division 1", "round": 2, "instance": 1, "matchnum": 27, "field": "Einstein", "red1": "21246D", "red2": "11729A", "red3": "", "redsit": "", "blue1": "43428A", "blue2": "254A", "blue3": "", "bluesit": "", "redscore": 15, "bluescore": 19, "scored": 1, "scheduled": "2018-11-17T20:18:00+00:00"}, {"sku": "RE-VRC-18-6528", "division": "Division 1", "round": 2, "instance": 1, "matchnum": 28, "field": "Tesla", "red1": "920B", "red2": "6374X", "red3": "", "redsit": "", "blue1": "315X", "blue2": "43426A", "blue3": "", "bluesit": "", "redscore": 8, "bluescore": 19, "scored": 1, "scheduled": "2018-11-17T20:21:00+00:00"}, {"sku": "RE-VRC-18-6528", "division": "Division 1", "round": 2, "instance": 1, "matchnum": 29, "field": "Einstein", "red1": "6374B", "red2": "7916A", "red3": "", "redsit": "", "blue1": "1868K", "blue2": "139A", "blue3": "", "bluesit": "", "redscore": 9, "bluescore": 17, "scored": 1, "scheduled": "2018-11-17T20:24:00+00:00"}, {"sku": "RE-VRC-18-6528", "division": "Division 1", "round": 2, "instance": 1, "matchnum": 30, "field": "Tesla", "red1": "79687A", "red2": "5776T", "red3": "", "redsit": "", "blue1": "1868A", "blue2": "5776E", "blue3": "", "bluesit": "", "redscore": 19, "bluescore": 18, "scored": 1, "scheduled": "2018-11-17T20:27:00+00:00"}, {"sku": "RE-VRC-18-6528", "division": "Division 1", "round": 2, "instance": 1, "matchnum": 31, "field": "Einstein", "red1": "88909D", "red2": "43426C", "red3": "", "redsit": "", "blue1": "920A", "blue2": "94927A", "blue3": "", "bluesit": "", "redscore": 7, "bluescore": 21, "scored": 1, "scheduled": "2018-11-17T21:00:00+00:00"}, {"sku": "RE-VRC-18-6528", "division": "Division 1", "round": 2, "instance": 1, "matchnum": 32, "field": "Tesla", "red1": "6627X", "red2": "6374A", "red3": "", "redsit": "", "blue1": "254B", "blue2": "95070C", "blue3": "", "bluesit": "", "redscore": 32, "bluescore": 4, "scored": 1, "scheduled": "2018-11-17T21:03:00+00:00"}, {"sku": "RE-VRC-18-6528", "division": "Division 1", "round": 2, "instance": 1, "matchnum": 33, "field": "Einstein", "red1": "74264A", "red2": "88811A", "red3": "", "redsit": "", "blue1": "315Y", "blue2": "5776X", "blue3": "", "bluesit": "", "redscore": 6, "bluescore": 20, "scored": 1, "scheduled": "2018-11-17T21:06:00+00:00"}, {"sku": "RE-VRC-18-6528", "division": "Division 1", "round": 2, "instance": 1, "matchnum": 34, "field": "Tesla", "red1": "254A", "red2": "315R", "red3": "", "redsit": "", "blue1": "254F", "blue2": "920D", "blue3": "", "bluesit": "", "redscore": 28, "bluescore": 8, "scored": 1, "scheduled": "2018-11-17T21:09:00+00:00"}, {"sku": "RE-VRC-18-6528", "division": "Division 1", "round": 2, "instance": 1, "matchnum": 35, "field": "Einstein", "red1": "88909Y", "red2": "95070A", "red3": "", "redsit": "", "blue1": "1868Z", "blue2": "254W", "blue3": "", "bluesit": "", "redscore": 16, "bluescore": 12, "scored": 1, "scheduled": "2018-11-17T21:12:00+00:00"}, {"sku": "RE-VRC-18-6528", "division": "Division 1", "round": 2, "instance": 1, "matchnum": 36, "field": "Tesla", "red1": "5297C", "red2": "88909X", "red3": "", "redsit": "", "blue1": "4008A", "blue2": "37880G", "blue3": "", "bluesit": "", "redscore": 19, "bluescore": 10, "scored": 1, "scheduled": "2018-11-17T21:15:00+00:00"}, {"sku": "RE-VRC-18-6528", "division": "Division 1", "round": 2, "instance": 1, "matchnum": 37, "field": "Einstein", "red1": "6374X", "red2": "2882R", "red3": "", "redsit": "", "blue1": "94065J", "blue2": "920C", "blue3": "", "bluesit": "", "redscore": 14, "bluescore": 21, "scored": 1, "scheduled": "2018-11-17T21:18:00+00:00"}, {"sku": "RE-VRC-18-6528", "division": "Division 1", "round": 2, "instance": 1, "matchnum": 38, "field": "Tesla", "red1": "95070B", "red2": "11101A", "red3": "", "redsit": "", "blue1": "95070D", "blue2": "6374B", "blue3": "", "bluesit": "", "redscore": 30, "bluescore": 4, "scored": 1, "scheduled": "2018-11-17T21:21:00+00:00"}, {"sku": "RE-VRC-18-6528", "division": "Division 1", "round": 2, "instance": 1, "matchnum": 39, "field": "Einstein", "red1": "5776A", "red2": "254D", "red3": "", "redsit": "", "blue1": "5776E", "blue2": "920B", "blue3": "", "bluesit": "", "redscore": 8, "bluescore": 23, "scored": 1, "scheduled": "2018-11-17T21:24:00+00:00"}, {"sku": "RE-VRC-18-6528", "division": "Division 1", "round": 2, "instance": 1, "matchnum": 40, "field": "Tesla", "red1": "5327C", "red2": "5297D", "red3": "", "redsit": "", "blue1": "7916A", "blue2": "11729A", "blue3": "", "bluesit": "", "redscore": 23, "bluescore": 3, "scored": 1, "scheduled": "2018-11-17T21:27:00+00:00"}, {"sku": "RE-VRC-18-6528", "division": "Division 1", "round": 2, "instance": 1, "matchnum": 41, "field": "Einstein", "red1": "5297A", "red2": "139A", "red3": "", "redsit": "", "blue1": "315X", "blue2": "86868R", "blue3": "", "bluesit": "", "redscore": 2, "bluescore": 33, "scored": 1, "scheduled": "2018-11-17T21:30:00+00:00"}, {"sku": "RE-VRC-18-6528", "division": "Division 1", "round": 2, "instance": 1, "matchnum": 42, "field": "Tesla", "red1": "1868X", "red2": "315G", "red3": "", "redsit": "", "blue1": "6374G", "blue2": "254X", "blue3": "", "bluesit": "", "redscore": 33, "bluescore": 3, "scored": 1, "scheduled": "2018-11-17T21:33:00+00:00"}, {"sku": "RE-VRC-18-6528", "division": "Division 1", "round": 2, "instance": 1, "matchnum": 43, "field": "Einstein", "red1": "43426A", "red2": "254C", "red3": "", "redsit": "", "blue1": "21246D", "blue2": "8000B", "blue3": "", "bluesit": "", "redscore": 9, "bluescore": 24, "scored": 1, "scheduled": "2018-11-17T21:36:00+00:00"}, {"sku": "RE-VRC-18-6528", "division": "Division 1", "round": 2, "instance": 1, "matchnum": 44, "field": "Tesla", "red1": "1868K", "red2": "88909A", "red3": "", "redsit": "", "blue1": "43428A", "blue2": "5297B", "blue3": "", "bluesit": "", "redscore": 21, "bluescore": 7, "scored": 1, "scheduled": "2018-11-17T21:39:00+00:00"}, {"sku": "RE-VRC-18-6528", "division": "Division 1", "round": 2, "instance": 1, "matchnum": 45, "field": "Einstein", "red1": "254F", "red2": "94927A", "red3": "", "redsit": "", "blue1": "5776T", "blue2": "88909X", "blue3": "", "bluesit": "", "redscore": 14, "bluescore": 21, "scored": 1, "scheduled": "2018-11-17T21:42:00+00:00"}, {"sku": "RE-VRC-18-6528", "division": "Division 1", "round": 2, "instance": 1, "matchnum": 46, "field": "Tesla", "red1": "37880G", "red2": "95070A", "red3": "", "redsit": "", "blue1": "6374X", "blue2": "88811A", "blue3": "", "bluesit": "", "redscore": 20, "bluescore": 11, "scored": 1, "scheduled": "2018-11-17T21:45:00+00:00"}, {"sku": "RE-VRC-18-6528", "division": "Division 1", "round": 2, "instance": 1, "matchnum": 47, "field": "Einstein", "red1": "5297D", "red2": "74264A", "red3": "", "redsit": "", "blue1": "6627X", "blue2": "94065J", "blue3": "", "bluesit": "", "redscore": 4, "bluescore": 28, "scored": 1, "scheduled": "2018-11-17T21:48:00+00:00"}, {"sku": "RE-VRC-18-6528", "division": "Division 1", "round": 2, "instance": 1, "matchnum": 48, "field": "Tesla", "red1": "254W", "red2": "4008A", "red3": "", "redsit": "", "blue1": "254A", "blue2": "11101A", "blue3": "", "bluesit": "", "redscore": 7, "bluescore": 26, "scored": 1, "scheduled": "2018-11-17T21:51:00+00:00"}, {"sku": "RE-VRC-18-6528", "division": "Division 1", "round": 2, "instance": 1, "matchnum": 49, "field": "Einstein", "red1": "79687A", "red2": "5776A", "red3": "", "redsit": "", "blue1": "2882R", "blue2": "6374A", "blue3": "", "bluesit": "", "redscore": 17, "bluescore": 12, "scored": 1, "scheduled": "2018-11-17T21:54:00+00:00"}, {"sku": "RE-VRC-18-6528", "division": "Division 1", "round": 2, "instance": 1, "matchnum": 50, "field": "Tesla", "red1": "6374G", "red2": "5776X", "red3": "", "redsit": "", "blue1": "43426C", "blue2": "8000B", "blue3": "", "bluesit": "", "redscore": 16, "bluescore": 13, "scored": 1, "scheduled": "2018-11-17T21:57:00+00:00"}, {"sku": "RE-VRC-18-6528", "division": "Division 1", "round": 2, "instance": 1, "matchnum": 51, "field": "Einstein", "red1": "254X", "red2": "7916A", "red3": "", "redsit": "", "blue1": "43426A", "blue2": "920A", "blue3": "", "bluesit": "", "redscore": 9, "bluescore": 19, "scored": 1, "scheduled": "2018-11-17T22:00:00+00:00"}, {"sku": "RE-VRC-18-6528", "division": "Division 1", "round": 2, "instance": 1, "matchnum": 52, "field": "Tesla", "red1": "254B", "red2": "88909D", "red3": "", "redsit": "", "blue1": "1868X", "blue2": "88909A", "blue3": "", "bluesit": "", "redscore": 12, "bluescore": 14, "scored": 1, "scheduled": "2018-11-17T22:03:00+00:00"}, {"sku": "RE-VRC-18-6528", "division": "Division 1", "round": 2, "instance": 1, "matchnum": 53, "field": "Einstein", "red1": "1868Z", "red2": "5327C", "red3": "", "redsit": "", "blue1": "95070B", "blue2": "920C", "blue3": "", "bluesit": "", "redscore": 12, "bluescore": 23, "scored": 1, "scheduled": "2018-11-17T22:06:00+00:00"}, {"sku": "RE-VRC-18-6528", "division": "Division 1", "round": 2, "instance": 1, "matchnum": 54, "field": "Tesla", "red1": "6374B", "red2": "21246D", "red3": "", "redsit": "", "blue1": "88909Y", "blue2": "315Y", "blue3": "", "bluesit": "", "redscore": 14, "bluescore": 11, "scored": 1, "scheduled": "2018-11-17T22:09:00+00:00"}, {"sku": "RE-VRC-18-6528", "division": "Division 1", "round": 2, "instance": 1, "matchnum": 55, "field": "Einstein", "red1": "86868R", "red2": "95070C", "red3": "", "redsit": "", "blue1": "5776T", "blue2": "920B", "blue3": "", "bluesit": "", "redscore": 22, "bluescore": 13, "scored": 1, "scheduled": "2018-11-17T22:12:00+00:00"}, {"sku": "RE-VRC-18-6528", "division": "Division 1", "round": 2, "instance": 1, "matchnum": 56, "field": "Tesla", "red1": "254D", "red2": "1868A", "red3": "", "redsit": "", "blue1": "5297A", "blue2": "43428A", "blue3": "", "bluesit": "", "redscore": 16, "bluescore": 5, "scored": 1, "scheduled": "2018-11-17T22:15:00+00:00"}, {"sku": "RE-VRC-18-6528", "division": "Division 1", "round": 2, "instance": 1, "matchnum": 57, "field": "Einstein", "red1": "315X", "red2": "5297C", "red3": "", "redsit": "", "blue1": "1868K", "blue2": "315G", "blue3": "", "bluesit": "", "redscore": 12, "bluescore": 23, "scored": 1, "scheduled": "2018-11-17T22:18:00+00:00"}, {"sku": "RE-VRC-18-6528", "division": "Division 1", "round": 2, "instance": 1, "matchnum": 58, "field": "Tesla", "red1": "5297B", "red2": "920D", "red3": "", "redsit": "", "blue1": "254C", "blue2": "11729A", "blue3": "", "bluesit": "", "redscore": 19, "bluescore": 7, "scored": 1, "scheduled": "2018-11-17T22:21:00+00:00"}, {"sku": "RE-VRC-18-6528", "division": "Division 1", "round": 2, "instance": 1, "matchnum": 59, "field": "Einstein", "red1": "5776E", "red2": "315R", "red3": "", "redsit": "", "blue1": "139A", "blue2": "95070D", "blue3": "", "bluesit": "", "redscore": 24, "bluescore": 12, "scored": 1, "scheduled": "2018-11-17T22:24:00+00:00"}, {"sku": "RE-VRC-18-6528", "division": "Division 1", "round": 2, "instance": 1, "matchnum": 60, "field": "Tesla", "red1": "920A", "red2": "37880G", "red3": "", "redsit": "", "blue1": "79687A", "blue2": "6627X", "blue3": "", "bluesit": "", "redscore": 9, "bluescore": 27, "scored": 1, "scheduled": "2018-11-17T22:27:00+00:00"}, {"sku": "RE-VRC-18-6528", "division": "Division 1", "round": 2, "instance": 1, "matchnum": 61, "field": "Einstein", "red1": "7916A", "red2": "88909X", "red3": "", "redsit": "", "blue1": "95070B", "blue2": "1868X", "blue3": "", "bluesit": "", "redscore": 24, "bluescore": 6, "scored": 1, "scheduled": "2018-11-17T22:30:00+00:00"}, {"sku": "RE-VRC-18-6528", "division": "Division 1", "round": 2, "instance": 1, "matchnum": 62, "field": "Tesla", "red1": "88811A", "red2": "94927A", "red3": "", "redsit": "", "blue1": "5297D", "blue2": "6374A", "blue3": "", "bluesit": "", "redscore": 23, "bluescore": 6, "scored": 1, "scheduled": "2018-11-17T22:33:00+00:00"}, {"sku": "RE-VRC-18-6528", "division": "Division 1", "round": 2, "instance": 1, "matchnum": 63, "field": "Einstein", "red1": "5297A", "red2": "4008A", "red3": "", "redsit": "", "blue1": "5327C", "blue2": "43426A", "blue3": "", "bluesit": "", "redscore": 4, "bluescore": 31, "scored": 1, "scheduled": "2018-11-17T22:36:00+00:00"}, {"sku": "RE-VRC-18-6528", "division": "Division 1", "round": 2, "instance": 1, "matchnum": 64, "field": "Tesla", "red1": "43428A", "red2": "920C", "red3": "", "redsit": "", "blue1": "88909D", "blue2": "315G", "blue3": "", "bluesit": "", "redscore": 3, "bluescore": 30, "scored": 1, "scheduled": "2018-11-17T22:39:00+00:00"}, {"sku": "RE-VRC-18-6528", "division": "Division 1", "round": 2, "instance": 1, "matchnum": 65, "field": "Einstein", "red1": "920B", "red2": "1868Z", "red3": "", "redsit": "", "blue1": "21246D", "blue2": "1868K", "blue3": "", "bluesit": "", "redscore": 8, "bluescore": 27, "scored": 1, "scheduled": "2018-11-17T22:42:00+00:00"}, {"sku": "RE-VRC-18-6528", "division": "Division 1", "round": 2, "instance": 1, "matchnum": 66, "field": "Tesla", "red1": "95070A", "red2": "254C", "red3": "", "redsit": "", "blue1": "74264A", "blue2": "315R", "blue3": "", "bluesit": "", "redscore": 4, "bluescore": 25, "scored": 1, "scheduled": "2018-11-17T22:45:00+00:00"}, {"sku": "RE-VRC-18-6528", "division": "Division 1", "round": 2, "instance": 1, "matchnum": 67, "field": "Einstein", "red1": "6374X", "red2": "5776X", "red3": "", "redsit": "", "blue1": "95070C", "blue2": "6374B", "blue3": "", "bluesit": "", "redscore": 16, "bluescore": 8, "scored": 1, "scheduled": "2018-11-17T22:48:00+00:00"}, {"sku": "RE-VRC-18-6528", "division": "Division 1", "round": 2, "instance": 1, "matchnum": 68, "field": "Tesla", "red1": "94065J", "red2": "5297B", "red3": "", "redsit": "", "blue1": "139A", "blue2": "6374G", "blue3": "", "bluesit": "", "redscore": 7, "bluescore": 24, "scored": 1, "scheduled": "2018-11-17T22:51:00+00:00"}, {"sku": "RE-VRC-18-6528", "division": "Division 1", "round": 2, "instance": 1, "matchnum": 69, "field": "Einstein", "red1": "8000B", "red2": "11729A", "red3": "", "redsit": "", "blue1": "254B", "blue2": "95070D", "blue3": "", "bluesit": "", "redscore": 20, "bluescore": 9, "scored": 1, "scheduled": "2018-11-17T22:54:00+00:00"}, {"sku": "RE-VRC-18-6528", "division": "Division 1", "round": 2, "instance": 1, "matchnum": 70, "field": "Tesla", "red1": "254F", "red2": "315Y", "red3": "", "redsit": "", "blue1": "5297C", "blue2": "86868R", "blue3": "", "bluesit": "", "redscore": 12, "bluescore": 24, "scored": 1, "scheduled": "2018-11-17T22:57:00+00:00"}, {"sku": "RE-VRC-18-6528", "division": "Division 1", "round": 2, "instance": 1, "matchnum": 71, "field": "Einstein", "red1": "315X", "red2": "5776T", "red3": "", "redsit": "", "blue1": "254W", "blue2": "254D", "blue3": "", "bluesit": "", "redscore": 24, "bluescore": 8, "scored": 1, "scheduled": "2018-11-17T23:00:00+00:00"}, {"sku": "RE-VRC-18-6528", "division": "Division 1", "round": 2, "instance": 1, "matchnum": 72, "field": "Tesla", "red1": "2882R", "red2": "920D", "red3": "", "redsit": "", "blue1": "43426C", "blue2": "88909A", "blue3": "", "bluesit": "", "redscore": 21, "bluescore": 11, "scored": 1, "scheduled": "2018-11-17T23:03:00+00:00"}, {"sku": "RE-VRC-18-6528", "division": "Division 1", "round": 2, "instance": 1, "matchnum": 73, "field": "Einstein", "red1": "5776A", "red2": "254X", "red3": "", "redsit": "", "blue1": "254A", "blue2": "1868A", "blue3": "", "bluesit": "", "redscore": 13, "bluescore": 16, "scored": 1, "scheduled": "2018-11-17T23:06:00+00:00"}, {"sku": "RE-VRC-18-6528", "division": "Division 1", "round": 2, "instance": 1, "matchnum": 74, "field": "Tesla", "red1": "5776E", "red2": "88909Y", "red3": "", "redsit": "", "blue1": "11101A", "blue2": "43428A", "blue3": "", "bluesit": "", "redscore": 27, "bluescore": 6, "scored": 1, "scheduled": "2018-11-17T23:09:00+00:00"}, {"sku": "RE-VRC-18-6528", "division": "Division 1", "round": 6, "instance": 1, "matchnum": 1, "field": "", "red1": "315G", "red2": "315R", "red3": "", "redsit": "", "blue1": "88909A", "blue2": "94927A", "blue3": "", "bluesit": "", "redscore": 29, "bluescore": 9, "scored": 1, "scheduled": "1970-01-01T00:00:00+00:00"}, {"sku": "RE-VRC-18-6528", "division": "Division 1", "round": 6, "instance": 2, "matchnum": 1, "field": "", "red1": "315X", "red2": "8000B", "red3": "", "redsit": "", "blue1": "5776T", "blue2": "5776E", "blue3": "", "bluesit": "", "redscore": 19, "bluescore": 11, "scored": 1, "scheduled": "1970-01-01T00:00:00+00:00"}, {"sku": "RE-VRC-18-6528", "division": "Division 1", "round": 6, "instance": 3, "matchnum": 1, "field": "", "red1": "88909X", "red2": "1868A", "red3": "", "redsit": "", "blue1": "11101A", "blue2": "5776A", "blue3": "", "bluesit": "", "redscore": 14, "bluescore": 17, "scored": 1, "scheduled": "1970-01-01T00:00:00+00:00"}, {"sku": "RE-VRC-18-6528", "division": "Division 1", "round": 6, "instance": 4, "matchnum": 1, "field": "", "red1": "254A", "red2": "88909Y", "red3": "", "redsit": "", "blue1": "95070B", "blue2": "95070A", "blue3": "", "bluesit": "", "redscore": 21, "bluescore": 11, "scored": 1, "scheduled": "1970-01-01T00:00:00+00:00"}, {"sku": "RE-VRC-18-6528", "division": "Division 1", "round": 6, "instance": 5, "matchnum": 1, "field": "", "red1": "6627X", "red2": "86868R", "red3": "", "redsit": "", "blue1": "5297C", "blue2": "1868X", "blue3": "", "bluesit": "", "redscore": 28, "bluescore": 7, "scored": 1, "scheduled": "1970-01-01T00:00:00+00:00"}, {"sku": "RE-VRC-18-6528", "division": "Division 1", "round": 6, "instance": 6, "matchnum": 1, "field": "", "red1": "5327C", "red2": "139A", "red3": "", "redsit": "", "blue1": "5776X", "blue2": "315Y", "blue3": "", "bluesit": "", "redscore": 17, "bluescore": 6, "scored": 1, "scheduled": "1970-01-01T00:00:00+00:00"}, {"sku": "RE-VRC-18-6528", "division": "Division 1", "round": 6, "instance": 7, "matchnum": 1, "field": "", "red1": "1868K", "red2": "94065J", "red3": "", "redsit": "", "blue1": "79687A", "blue2": "43426A", "blue3": "", "bluesit": "", "redscore": 28, "bluescore": 6, "scored": 1, "scheduled": "1970-01-01T00:00:00+00:00"}, {"sku": "RE-VRC-18-6528", "division": "Division 1", "round": 6, "instance": 8, "matchnum": 1, "field": "", "red1": "21246D", "red2": "920C", "red3": "", "redsit": "", "blue1": "920A", "blue2": "920D", "blue3": "", "bluesit": "", "redscore": 30, "bluescore": 2, "scored": 1, "scheduled": "1970-01-01T00:00:00+00:00"}, {"sku": "RE-VRC-18-6528", "division": "Division 1", "round": 3, "instance": 1, "matchnum": 1, "field": "", "red1": "315G", "red2": "315R", "red3": "", "redsit": "", "blue1": "315X", "blue2": "8000B", "blue3": "", "bluesit": "", "redscore": 18, "bluescore": 14, "scored": 1, "scheduled": "1970-01-01T00:00:00+00:00"}, {"sku": "RE-VRC-18-6528", "division": "Division 1", "round": 3, "instance": 2, "matchnum": 1, "field": "", "red1": "11101A", "red2": "5776A", "red3": "", "redsit": "", "blue1": "254A", "blue2": "88909Y", "blue3": "", "bluesit": "", "redscore": 14, "bluescore": 13, "scored": 1, "scheduled": "1970-01-01T00:00:00+00:00"}, {"sku": "RE-VRC-18-6528", "division": "Division 1", "round": 3, "instance": 3, "matchnum": 1, "field": "", "red1": "6627X", "red2": "86868R", "red3": "", "redsit": "", "blue1": "5327C", "blue2": "139A", "blue3": "", "bluesit": "", "redscore": 17, "bluescore": 16, "scored": 1, "scheduled": "1970-01-01T00:00:00+00:00"}, {"sku": "RE-VRC-18-6528", "division": "Division 1", "round": 3, "instance": 4, "matchnum": 1, "field": "", "red1": "1868K", "red2": "94065J", "red3": "", "redsit": "", "blue1": "21246D", "blue2": "920C", "blue3": "", "bluesit": "", "redscore": 10, "bluescore": 31, "scored": 1, "scheduled": "1970-01-01T00:00:00+00:00"}, {"sku": "RE-VRC-18-6528", "division": "Division 1", "round": 4, "instance": 1, "matchnum": 1, "field": "", "red1": "315G", "red2": "315R", "red3": "", "redsit": "", "blue1": "11101A", "blue2": "5776A", "blue3": "", "bluesit": "", "redscore": 21, "bluescore": 12, "scored": 1, "scheduled": "1970-01-01T00:00:00+00:00"}, {"sku": "RE-VRC-18-6528", "division": "Division 1", "round": 4, "instance": 2, "matchnum": 1, "field": "", "red1": "6627X", "red2": "86868R", "red3": "", "redsit": "", "blue1": "21246D", "blue2": "920C", "blue3": "", "bluesit": "", "redscore": 24, "bluescore": 11, "scored": 1, "scheduled": "1970-01-01T00:00:00+00:00"}, {"sku": "RE-VRC-18-6528", "division": "Division 1", "round": 5, "instance": 1, "matchnum": 1, "field": "", "red1": "315G", "red2": "315R", "red3": "", "redsit": "", "blue1": "6627X", "blue2": "86868R", "blue3": "", "bluesit": "", "redscore": 16, "bluescore": 20, "scored": 1, "scheduled": "1970-01-01T00:00:00+00:00"}], "rankings": [{"sku": "RE-VRC-18-6528", "division": "Division 1", "rank": 1, "team": "315G", "wins": 5, "losses": 0, "ties": 0, "wp": 10, "ap": 16, "sp": 34, "trsp": 29, "max_score": 33, "opr": 20.5539, "dpr": -1.7049, "ccwm": 22.2588}, {"sku": "RE-VRC-18-6528", "division": "Division 1", "rank": 2, "team": "6627X", "wins": 5, "losses": 0, "ties": 0, "wp": 10, "ap": 16, "sp": 31, "trsp": 28, "max_score": 32, "opr": 20.7967, "dpr": -2.56779, "ccwm": 23.3645}, {"sku": "RE-VRC-18-6528", "division": "Division 1", "rank": 3, "team": "315R", "wins": 5, "losses": 0, "ties": 0, "wp": 10, "ap": 12, "sp": 47, "trsp": 27, "max_score": 29, "opr": 18.3253, "dpr": -2.51214, "ccwm": 20.8374}, {"sku": "RE-VRC-18-6528", "division": "Division 1", "rank": 4, "team": "1868K", "wins": 5, "losses": 0, "ties": 0, "wp": 10, "ap": 12, "sp": 47, "trsp": 14, "max_score": 28, "opr": 9.72791, "dpr": 5.03704, "ccwm": 4.69087}, {"sku": "RE-VRC-18-6528", "division": "Division 1", "rank": 5, "team": "88909X", "wins": 5, "losses": 0, "ties": 0, "wp": 10, "ap": 12, "sp": 46, "trsp": 16, "max_score": 27, "opr": 13.5369, "dpr": 1.67512, "ccwm": 11.8618}, {"sku": "RE-VRC-18-6528", "division": "Division 1", "rank": 6, "team": "254A", "wins": 4, "losses": 1, "ties": 0, "wp": 8, "ap": 16, "sp": 56, "trsp": 17, "max_score": 28, "opr": 11.1071, "dpr": 7.92951, "ccwm": 3.17761}, {"sku": "RE-VRC-18-6528", "division": "Division 1", "rank": 7, "team": "21246D", "wins": 4, "losses": 1, "ties": 0, "wp": 8, "ap": 16, "sp": 49, "trsp": 32, "max_score": 31, "opr": 15.9193, "dpr": 0.540382, "ccwm": 15.3789}, {"sku": "RE-VRC-18-6528", "division": "Division 1", "rank": 8, "team": "5327C", "wins": 4, "losses": 1, "ties": 0, "wp": 8, "ap": 16, "sp": 44, "trsp": 22, "max_score": 32, "opr": 17.9039, "dpr": 1.8468, "ccwm": 16.0571}, {"sku": "RE-VRC-18-6528", "division": "Division 1", "rank": 9, "team": "315X", "wins": 4, "losses": 1, "ties": 0, "wp": 8, "ap": 16, "sp": 37, "trsp": 11, "max_score": 33, "opr": 12.1284, "dpr": 3.61992, "ccwm": 8.50848}, {"sku": "RE-VRC-18-6528", "division": "Division 1", "rank": 10, "team": "94065J", "wins": 4, "losses": 1, "ties": 0, "wp": 8, "ap": 16, "sp": 33, "trsp": 9, "max_score": 35, "opr": 12.6872, "dpr": 2.85239, "ccwm": 9.83479}, {"sku": "RE-VRC-18-6528", "division": "Division 1", "rank": 11, "team": "5776T", "wins": 4, "losses": 1, "ties": 0, "wp": 8, "ap": 8, "sp": 54, "trsp": 10, "max_score": 35, "opr": 12.6451, "dpr": 7.18976, "ccwm": 5.45533}, {"sku": "RE-VRC-18-6528", "division": "Division 1", "rank": 12, "team": "86868R", "wins": 4, "losses": 1, "ties": 0, "wp": 8, "ap": 8, "sp": 38, "trsp": 28, "max_score": 33, "opr": 18.2471, "dpr": 0.017418, "ccwm": 18.2297}, {"sku": "RE-VRC-18-6528", "division": "Division 1", "rank": 13, "team": "5776X", "wins": 3, "losses": 1, "ties": 1, "wp": 7, "ap": 12, "sp": 46, "trsp": 24, "max_score": 20, "opr": 8.82654, "dpr": 3.24189, "ccwm": 5.58464}, {"sku": "RE-VRC-18-6528", "division": "Division 1", "rank": 14, "team": "1868A", "wins": 3, "losses": 2, "ties": 0, "wp": 6, "ap": 16, "sp": 46, "trsp": 8, "max_score": 25, "opr": 8.1501, "dpr": 1.65664, "ccwm": 6.49346}, {"sku": "RE-VRC-18-6528", "division": "Division 1", "rank": 15, "team": "5776E", "wins": 3, "losses": 2, "ties": 0, "wp": 6, "ap": 12, "sp": 55, "trsp": 25, "max_score": 27, "opr": 11.3132, "dpr": 11.2448, "ccwm": 0.0684007}, {"sku": "RE-VRC-18-6528", "division": "Division 1", "rank": 16, "team": "920A", "wins": 3, "losses": 2, "ties": 0, "wp": 6, "ap": 12, "sp": 43, "trsp": 17, "max_score": 32, "opr": 8.5404, "dpr": 8.69035, "ccwm": -0.14995}, {"sku": "RE-VRC-18-6528", "division": "Division 1", "rank": 17, "team": "95070B", "wins": 3, "losses": 2, "ties": 0, "wp": 6, "ap": 12, "sp": 41, "trsp": 26, "max_score": 30, "opr": 9.12936, "dpr": 7.1581, "ccwm": 1.97126}, {"sku": "RE-VRC-18-6528", "division": "Division 1", "rank": 18, "team": "11101A", "wins": 3, "losses": 2, "ties": 0, "wp": 6, "ap": 12, "sp": 34, "trsp": 19, "max_score": 30, "opr": 12.8996, "dpr": 6.22012, "ccwm": 6.67945}, {"sku": "RE-VRC-18-6528", "division": "Division 1", "rank": 19, "team": "79687A", "wins": 3, "losses": 2, "ties": 0, "wp": 6, "ap": 8, "sp": 65, "trsp": 24, "max_score": 27, "opr": 7.24016, "dpr": 10.2382, "ccwm": -2.998}, {"sku": "RE-VRC-18-6528", "division": "Division 1", "rank": 20, "team": "5297C", "wins": 3, "losses": 2, "ties": 0, "wp": 6, "ap": 8, "sp": 46, "trsp": 2, "max_score": 25, "opr": 2.72245, "dpr": 13.5086, "ccwm": -10.7862}, {"sku": "RE-VRC-18-6528", "division": "Division 1", "rank": 21, "team": "1868X", "wins": 3, "losses": 2, "ties": 0, "wp": 6, "ap": 8, "sp": 42, "trsp": 5, "max_score": 33, "opr": 7.72954, "dpr": 8.46046, "ccwm": -0.73092}, {"sku": "RE-VRC-18-6528", "division": "Division 1", "rank": 22, "team": "920C", "wins": 3, "losses": 2, "ties": 0, "wp": 6, "ap": 8, "sp": 42, "trsp": 22, "max_score": 31, "opr": 7.86671, "dpr": 12.6223, "ccwm": -4.7556}, {"sku": "RE-VRC-18-6528", "division": "Division 1", "rank": 23, "team": "88909Y", "wins": 3, "losses": 2, "ties": 0, "wp": 6, "ap": 8, "sp": 40, "trsp": 20, "max_score": 27, "opr": 9.09857, "dpr": 2.02753, "ccwm": 7.07104}, {"sku": "RE-VRC-18-6528", "division": "Division 1", "rank": 24, "team": "43426A", "wins": 3, "losses": 2, "ties": 0, "wp": 6, "ap": 8, "sp": 37, "trsp": 5, "max_score": 31, "opr": 7.20649, "dpr": 7.50948, "ccwm": -0.302987}, {"sku": "RE-VRC-18-6528", "division": "Division 1", "rank": 25, "team": "920D", "wins": 3, "losses": 2, "ties": 0, "wp": 6, "ap": 8, "sp": 37, "trsp": 26, "max_score": 25, "opr": 9.99529, "dpr": 5.31396, "ccwm": 4.68133}, {"sku": "RE-VRC-18-6528", "division": "Division 1", "rank": 26, "team": "88909A", "wins": 3, "losses": 2, "ties": 0, "wp": 6, "ap": 4, "sp": 52, "trsp": 2, "max_score": 21, "opr": 6.91311, "dpr": 5.97736, "ccwm": 0.935744}, {"sku": "RE-VRC-18-6528", "division": "Division 1", "rank": 27, "team": "74264A", "wins": 3, "losses": 2, "ties": 0, "wp": 6, "ap": 4, "sp": 41, "trsp": 12, "max_score": 25, "opr": 5.13206, "dpr": 11.1738, "ccwm": -6.04173}, {"sku": "RE-VRC-18-6528", "division": "Division 1", "rank": 28, "team": "139A", "wins": 3, "losses": 2, "ties": 0, "wp": 6, "ap": 0, "sp": 34, "trsp": 38, "max_score": 24, "opr": 9.84203, "dpr": 5.82816, "ccwm": 4.01386}, {"sku": "RE-VRC-18-6528", "division": "Division 1", "rank": 29, "team": "95070A", "wins": 2, "losses": 2, "ties": 1, "wp": 5, "ap": 8, "sp": 42, "trsp": 32, "max_score": 20, "opr": 6.96844, "dpr": 10.5444, "ccwm": -3.57596}, {"sku": "RE-VRC-18-6528", "division": "Division 1", "rank": 30, "team": "315Y", "wins": 2, "losses": 3, "ties": 0, "wp": 4, "ap": 12, "sp": 49, "trsp": 16, "max_score": 24, "opr": 9.51576, "dpr": 5.02898, "ccwm": 4.48678}, {"sku": "RE-VRC-18-6528", "division": "Division 1", "rank": 31, "team": "94927A", "wins": 2, "losses": 3, "ties": 0, "wp": 4, "ap": 12, "sp": 45, "trsp": 32, "max_score": 23, "opr": 7.6783, "dpr": 5.93856, "ccwm": 1.73974}, {"sku": "RE-VRC-18-6528", "division": "Division 1", "rank": 32, "team": "7916A", "wins": 2, "losses": 3, "ties": 0, "wp": 4, "ap": 12, "sp": 31, "trsp": 33, "max_score": 24, "opr": 8.91427, "dpr": 1.98028, "ccwm": 6.93399}, {"sku": "RE-VRC-18-6528", "division": "Division 1", "rank": 33, "team": "2882R", "wins": 2, "losses": 3, "ties": 0, "wp": 4, "ap": 8, "sp": 63, "trsp": 21, "max_score": 21, "opr": 7.12524, "dpr": 11.2618, "ccwm": -4.1366}, {"sku": "RE-VRC-18-6528", "division": "Division 1", "rank": 34, "team": "1868Z", "wins": 2, "losses": 3, "ties": 0, "wp": 4, "ap": 8, "sp": 45, "trsp": 17, "max_score": 29, "opr": 4.90543, "dpr": 11.3258, "ccwm": -6.42042}, {"sku": "RE-VRC-18-6528", "division": "Division 1", "rank": 35, "team": "5776A", "wins": 2, "losses": 3, "ties": 0, "wp": 4, "ap": 8, "sp": 45, "trsp": 22, "max_score": 29, "opr": 6.64785, "dpr": 8.16641, "ccwm": -1.51856}, {"sku": "RE-VRC-18-6528", "division": "Division 1", "rank": 36, "team": "6374A", "wins": 2, "losses": 3, "ties": 0, "wp": 4, "ap": 8, "sp": 44, "trsp": 10, "max_score": 32, "opr": 5.18086, "dpr": 9.40218, "ccwm": -4.22132}, {"sku": "RE-VRC-18-6528", "division": "Division 1", "rank": 37, "team": "5297B", "wins": 2, "losses": 3, "ties": 0, "wp": 4, "ap": 8, "sp": 35, "trsp": 20, "max_score": 21, "opr": 1.26024, "dpr": 13.1798, "ccwm": -11.9195}, {"sku": "RE-VRC-18-6528", "division": "Division 1", "rank": 38, "team": "88811A", "wins": 2, "losses": 3, "ties": 0, "wp": 4, "ap": 8, "sp": 34, "trsp": 22, "max_score": 24, "opr": 8.72626, "dpr": 5.79066, "ccwm": 2.9356}, {"sku": "RE-VRC-18-6528", "division": "Division 1", "rank": 39, "team": "5297D", "wins": 2, "losses": 3, "ties": 0, "wp": 4, "ap": 8, "sp": 23, "trsp": 17, "max_score": 23, "opr": 2.64715, "dpr": 8.83814, "ccwm": -6.19099}, {"sku": "RE-VRC-18-6528", "division": "Division 1", "rank": 40, "team": "95070D", "wins": 2, "losses": 3, "ties": 0, "wp": 4, "ap": 4, "sp": 43, "trsp": 17, "max_score": 24, "opr": 8.31812, "dpr": 8.19419, "ccwm": 0.123933}, {"sku": "RE-VRC-18-6528", "division": "Division 1", "rank": 41, "team": "6374G", "wins": 2, "losses": 3, "ties": 0, "wp": 4, "ap": 4, "sp": 31, "trsp": 20, "max_score": 24, "opr": 4.91229, "dpr": 10.3432, "ccwm": -5.43095}, {"sku": "RE-VRC-18-6528", "division": "Division 1", "rank": 42, "team": "254D", "wins": 1, "losses": 3, "ties": 1, "wp": 3, "ap": 8, "sp": 40, "trsp": 14, "max_score": 16, "opr": 5.24005, "dpr": 8.41161, "ccwm": -3.17157}, {"sku": "RE-VRC-18-6528", "division": "Division 1", "rank": 43, "team": "254F", "wins": 1, "losses": 4, "ties": 0, "wp": 2, "ap": 16, "sp": 54, "trsp": 34, "max_score": 21, "opr": 4.92992, "dpr": 14.8774, "ccwm": -9.94747}, {"sku": "RE-VRC-18-6528", "division": "Division 1", "rank": 44, "team": "37880G", "wins": 1, "losses": 4, "ties": 0, "wp": 2, "ap": 16, "sp": 49, "trsp": 23, "max_score": 20, "opr": 4.59615, "dpr": 9.27603, "ccwm": -4.67988}, {"sku": "RE-VRC-18-6528", "division": "Division 1", "rank": 45, "team": "6374B", "wins": 1, "losses": 4, "ties": 0, "wp": 2, "ap": 12, "sp": 33, "trsp": 26, "max_score": 14, "opr": -1.30508, "dpr": 14.8896, "ccwm": -16.1947}, {"sku": "RE-VRC-18-6528", "division": "Division 1", "rank": 46, "team": "920B", "wins": 1, "losses": 4, "ties": 0, "wp": 2, "ap": 8, "sp": 45, "trsp": 17, "max_score": 23, "opr": 3.18191, "dpr": 8.66559, "ccwm": -5.48369}, {"sku": "RE-VRC-18-6528", "division": "Division 1", "rank": 47, "team": "43426C", "wins": 1, "losses": 4, "ties": 0, "wp": 2, "ap": 8, "sp": 42, "trsp": 14, "max_score": 20, "opr": 4.30455, "dpr": 11.7515, "ccwm": -7.44699}, {"sku": "RE-VRC-18-6528", "division": "Division 1", "rank": 48, "team": "254W", "wins": 1, "losses": 4, "ties": 0, "wp": 2, "ap": 8, "sp": 42, "trsp": 26, "max_score": 12, "opr": 1.60308, "dpr": 10.1659, "ccwm": -8.56277}, {"sku": "RE-VRC-18-6528", "division": "Division 1", "rank": 49, "team": "88909D", "wins": 1, "losses": 4, "ties": 0, "wp": 2, "ap": 8, "sp": 36, "trsp": 15, "max_score": 30, "opr": 4.62264, "dpr": 8.6101, "ccwm": -3.98746}, {"sku": "RE-VRC-18-6528", "division": "Division 1", "rank": 50, "team": "254B", "wins": 1, "losses": 4, "ties": 0, "wp": 2, "ap": 8, "sp": 34, "trsp": 12, "max_score": 22, "opr": 1.02096, "dpr": 13.2588, "ccwm": -12.2378}, {"sku": "RE-VRC-18-6528", "division": "Division 1", "rank": 51, "team": "6374X", "wins": 1, "losses": 4, "ties": 0, "wp": 2, "ap": 4, "sp": 52, "trsp": 18, "max_score": 16, "opr": 4.97998, "dpr": 9.56037, "ccwm": -4.58039}, {"sku": "RE-VRC-18-6528", "division": "Division 1", "rank": 52, "team": "8000B", "wins": 1, "losses": 4, "ties": 0, "wp": 2, "ap": 4, "sp": 46, "trsp": 11, "max_score": 24, "opr": 10.2468, "dpr": 2.35129, "ccwm": 7.89551}, {"sku": "RE-VRC-18-6528", "division": "Division 1", "rank": 53, "team": "4008A", "wins": 1, "losses": 4, "ties": 0, "wp": 2, "ap": 4, "sp": 43, "trsp": 36, "max_score": 24, "opr": 4.09875, "dpr": 15.704, "ccwm": -11.6053}, {"sku": "RE-VRC-18-6528", "division": "Division 1", "rank": 54, "team": "11729A", "wins": 1, "losses": 4, "ties": 0, "wp": 2, "ap": 4, "sp": 39, "trsp": 13, "max_score": 20, "opr": 1.43029, "dpr": 13.4086, "ccwm": -11.9784}, {"sku": "RE-VRC-18-6528", "division": "Division 1", "rank": 55, "team": "95070C", "wins": 1, "losses": 4, "ties": 0, "wp": 2, "ap": 4, "sp": 35, "trsp": 15, "max_score": 22, "opr": 2.40524, "dpr": 13.2927, "ccwm": -10.8874}, {"sku": "RE-VRC-18-6528", "division": "Division 1", "rank": 56, "team": "254C", "wins": 1, "losses": 4, "ties": 0, "wp": 2, "ap": 4, "sp": 28, "trsp": 19, "max_score": 19, "opr": 2.52809, "dpr": 9.67321, "ccwm": -7.14512}, {"sku": "RE-VRC-18-6528", "division": "Division 1", "rank": 57, "team": "5297A", "wins": 1, "losses": 4, "ties": 0, "wp": 2, "ap": 4, "sp": 25, "trsp": 29, "max_score": 19, "opr": -0.696554, "dpr": 14.6115, "ccwm": -15.3081}, {"sku": "RE-VRC-18-6528", "division": "Division 1", "rank": 58, "team": "43428A", "wins": 1, "losses": 4, "ties": 0, "wp": 2, "ap": 4, "sp": 25, "trsp": 15, "max_score": 19, "opr": 2.49331, "dpr": 8.71182, "ccwm": -6.21851}, {"sku": "RE-VRC-18-6528", "division": "Division 1", "rank": 59, "team": "254X", "wins": 0, "losses": 4, "ties": 1, "wp": 1, "ap": 8, "sp": 53, "trsp": 18, "max_score": 14, "opr": 2.83666, "dpr": 14.2478, "ccwm": -11.4112}], "skills": [{"sku": "RE-VRC-18-6528", "type": 2, "rank": 1, "team": "86868R", "program": "VRC", "attempts": 5, "score": 39}, {"sku": "RE-VRC-18-6528", "type": 0, "rank": 1, "team": "86868R", "program": "VRC", "attempts": 4, "score": 27}, {"sku": "RE-VRC-18-6528", "type": 1, "rank": 1, "team": "86868R", "program": "VRC", "attempts": 1, "score": 12}, {"sku": "RE-VRC-18-6528", "type": 2, "rank": 2, "team": "5776E", "program": "VRC", "attempts": 6, "score": 31}, {"sku": "RE-VRC-18-6528", "type": 0, "rank": 2, "team": "5776E", "program": "VRC", "attempts": 3, "score": 21}, {"sku": "RE-VRC-18-6528", "type": 1, "rank": 2, "team": "5776E", "program": "VRC", "attempts": 3, "score": 10}, {"sku": "RE-VRC-18-6528", "type": 2, "rank": 3, "team": "139A", "program": "VRC", "attempts": 4, "score": 29}, {"sku": "RE-VRC-18-6528", "type": 0, "rank": 3, "team": "139A", "program": "VRC", "attempts": 3, "score": 23}, {"sku": "RE-VRC-18-6528", "type": 1, "rank": 3, "team": "139A", "program": "VRC", "attempts": 1, "score": 6}, {"sku": "RE-VRC-18-6528", "type": 2, "rank": 4, "team": "6627X", "program": "VRC", "attempts": 6, "score": 27}, {"sku": "RE-VRC-18-6528", "type": 0, "rank": 4, "team": "6627X", "program": "VRC", "attempts": 4, "score": 22}, {"sku": "RE-VRC-18-6528", "type": 1, "rank": 4, "team": "6627X", "program": "VRC", "attempts": 2, "score": 5}, {"sku": "RE-VRC-18-6528", "type": 2, "rank": 5, "team": "88909X", "program": "VRC", "attempts": 8, "score": 26}, {"sku": "RE-VRC-18-6528", "type": 1, "rank": 5, "team": "88909X", "program": "VRC", "attempts": 2, "score": 15}, {"sku": "RE-VRC-18-6528", "type": 0, "rank": 5, "team": "88909X", "program": "VRC", "attempts": 6, "score": 11}, {"sku": "RE-VRC-18-6528", "type": 2, "rank": 6, "team": "2882R", "program": "VRC", "attempts": 5, "score": 22}, {"sku": "RE-VRC-18-6528", "type": 0, "rank": 6, "team": "2882R", "program": "VRC", "attempts": 3, "score": 15}, {"sku": "RE-VRC-18-6528", "type": 1, "rank": 6, "team": "2882R", "program": "VRC", "attempts": 2, "score": 7}, {"sku": "RE-VRC-18-6528", "type": 2, "rank": 7, "team": "94065J", "program": "VRC", "attempts": 2, "score": 20}, {"sku": "RE-VRC-18-6528", "type": 0, "rank": 7, "team": "94065J", "program": "VRC", "attempts": 1, "score": 16}, {"sku": "RE-VRC-18-6528", "type": 1, "rank": 7, "team": "94065J", "program": "VRC", "attempts": 1, "score": 4}, {"sku": "RE-VRC-18-6528", "type": 2, "rank": 8, "team": "5776A", "program": "VRC", "attempts": 2, "score": 20}, {"sku": "RE-VRC-18-6528", "type": 0, "rank": 8, "team": "5776A", "program": "VRC", "attempts": 1, "score": 16}, {"sku": "RE-VRC-18-6528", "type": 1, "rank": 8, "team": "5776A", "program": "VRC", "attempts": 1, "score": 4}, {"sku": "RE-VRC-18-6528", "type": 2, "rank": 9, "team": "5327C", "program": "VRC", "attempts": 1, "score": 19}, {"sku": "RE-VRC-18-6528", "type": 0, "rank": 9, "team": "5327C", "program": "VRC", "attempts": 1, "score": 19}, {"sku": "RE-VRC-18-6528", "type": 1, "rank": 9, "team": "5327C", "program": "VRC", "attempts": 0, "score": 0}, {"sku": "RE-VRC-18-6528", "type": 2, "rank": 10, "team": "5776T", "program": "VRC", "attempts": 1, "score": 18}, {"sku": "RE-VRC-18-6528", "type": 0, "rank": 10, "team": "5776T", "program": "VRC", "attempts": 1, "score": 18}, {"sku": "RE-VRC-18-6528", "type": 1, "rank": 10, "team": "5776T", "program": "VRC", "attempts": 0, "score": 0}, {"sku": "RE-VRC-18-6528", "type": 2, "rank": 11, "team": "5776X", "program": "VRC", "attempts": 5, "score": 15}, {"sku": "RE-VRC-18-6528", "type": 0, "rank": 11, "team": "5776X", "program": "VRC", "attempts": 3, "score": 10}, {"sku": "RE-VRC-18-6528", "type": 1, "rank": 11, "team": "5776X", "program": "VRC", "attempts": 2, "score": 5}, {"sku": "RE-VRC-18-6528", "type": 2, "rank": 12, "team": "315Y", "program": "VRC", "attempts": 2, "score": 11}, {"sku": "RE-VRC-18-6528", "type": 0, "rank": 12, "team": "315Y", "program": "VRC", "attempts": 1, "score": 7}, {"sku": "RE-VRC-18-6528", "type": 1, "rank": 12, "team": "315Y", "program": "VRC", "attempts": 1, "score": 4}, {"sku": "RE-VRC-18-6528", "type": 2, "rank": 13, "team": "88909Y", "program": "VRC", "attempts": 3, "score": 10}, {"sku": "RE-VRC-18-6528", "type": 0, "rank": 13, "team": "88909Y", "program": "VRC", "attempts": 3, "score": 10}, {"sku": "RE-VRC-18-6528", "type": 1, "rank": 13, "team": "88909Y", "program": "VRC", "attempts": 0, "score": 0}, {"sku": "RE-VRC-18-6528", "type": 2, "rank": 14, "team": "11729A", "program": "VRC", "attempts": 3, "score": 9}, {"sku": "RE-VRC-18-6528", "type": 0, "rank": 14, "team": "11729A", "program": "VRC", "attempts": 3, "score": 9}, {"sku": "RE-VRC-18-6528", "type": 1, "rank": 14, "team": "11729A", "program": "VRC", "attempts": 0, "score": 0}, {"sku": "RE-VRC-18-6528", "type": 2, "rank": 15, "team": "37880G", "program": "VRC", "attempts": 1, "score": 2}, {"sku": "RE-VRC-18-6528", "type": 0, "rank": 15, "team": "37880G", "program": "VRC", "attempts": 1, "score": 2}, {"sku": "RE-VRC-18-6528", "type": 1, "rank": 15, "team": "37880G", "program": "VRC", "attempts": 0, "score": 0}], "awards": [{"sku": "RE-VRC-18-6528", "name": "Tournament Champions (VRC/VEXU)", "team": "6627X", "qualifies": [], "order": 0}, {"sku": "RE-VRC-18-6528", "name": "Tournament Champions (VRC/VEXU)", "team": "86868R", "qualifies": [], "order": 0}, {"sku": "RE-VRC-18-6528", "name": "Amaze Award (VRC/VEXU)", "team": "5327C", "qualifies": [], "order": 1}, {"sku": "RE-VRC-18-6528", "name": "Design Award (VRC/VEXU)", "team": "139A", "qualifies": [], "order": 2}, {"sku": "RE-VRC-18-6528", "name": "Judges Award (VRC/VEXU)", "team": "94927A", "qualifies": [], "order": 3}, {"sku": "RE-VRC-18-6528", "name": "Tournament Finalists (VRC/VEXU)", "team": "315R", "qualifies": [], "order": 4}, {"sku": "RE-VRC-18-6528", "name": "Tournament Finalists (VRC/VEXU)", "team": "315G", "qualifies": [], "order": 4}, {"sku": "RE-VRC-18-6528", "name": "Robot Skills Champion (VRC/VEXU)", "team": "86868R", "qualifies": [], "order": 5}, {"sku": "RE-VRC-18-6528", "name": "Robot Skills 2nd Place (VRC/VEXU)", "team": "5776E", "qualifies": [], "order": 6}, {"sku": "RE-VRC-18-6528", "name": "Excellence Award - Middle School (VRC/VEXU)", "team": "94065J", "qualifies": [], "order": 7}, {"sku": "RE-VRC-18-6528", "name": "Excellence Award (High School)", "team": "6627X", "qualifies": [], "order": 8}]}